Workbook

Sheet Asimilado 
A2: EMPRESA | B2: Prima RT 2021
B3: 0.52779
B4: 0.68559 | C4: 0.69559
B5: 0.5
B6: 0.5
B7: 0.89384
B8: 0.5
B9: 2.50364
B10: 0.5
B11: 0.5
B12: 0.56122
B13: 0.9802 | C13: 0.9902
B14: 0.78573
B15: 0.62371 | C15: 0.63371
B16: 4.65325
B17: 0.52795
B18: 2.07534
B20: 4.65325

Sheet Tablas
O2: PROPUESTA
A3: LEY | H3: Tabla 1 | M3: Tabla 1 | R3: Tabla 2 | W3: Tabla 3 - Gerencial
H4: Niveles 1 a 4 del Tabulador | M4: Niveles 1 a 4 del Tabulador | R4: Niveles 5 y 6 del Tabulador | W4: Nivel 7 del Tabulador
A5: Años | B5: Vacaciones | C5: Prima Vac | D5: Aguinaldo | H5: Años | I5: Vacaciones | J5: Prima Vac | K5: Aguinaldo | M5: Años | N5: Vacaciones | O5: Prima Vac | P5: Aguinaldo | R5: Años | S5: Vacaciones | T5: Prima Vac | U5: Aguinaldo | W5: Años | X5: Vacaciones | Y5: Prima Vac | Z5: Aguinaldo
A6: 1 | B6: 12 | C6: 0.25 | D6: 15 | H6: 1 | I6: 12 | J6: 0.3 | K6: 17 | M6: 1 | N6: 8 | O6: 0.3 | P6: 17 | R6: 1 | S6: 10 | T6: 0.35 | U6: 18 | W6: 1 | X6: 12 | Y6: 0.35 | Z6: 20
A7: 2 | B7: 14 | C7: 0.25 | D7: 15 | H7: 2 | I7: 14 | J7: 0.3 | K7: 17 | M7: 2 | N7: 10 | O7: 0.3 | P7: 17 | R7: 2 | S7: 12 | T7: 0.35 | U7: 18 | W7: 2 | X7: 14 | Y7: 0.35 | Z7: 20
A8: 3 | B8: 16 | C8: 0.25 | D8: 15 | H8: 3 | I8: 16 | J8: 0.3 | K8: 17 | M8: 3 | N8: 12 | O8: 0.3 | P8: 17 | R8: 3 | S8: 14 | T8: 0.35 | U8: 18 | W8: 3 | X8: 16 | Y8: 0.35 | Z8: 20
A9: 4 | B9: 18 | C9: 0.25 | D9: 15 | H9: 4 | I9: 18 | J9: 0.3 | K9: 17 | M9: 4 | N9: 14 | O9: 0.3 | P9: 17 | R9: 4 | S9: 16 | T9: 0.35 | U9: 18 | W9: 4 | X9: 18 | Y9: 0.35 | Z9: 20
A10: 5 | B10: 20 | C10: 0.25 | D10: 15 | H10: 5 | I10: 20 | J10: 0.3 | K10: 17 | M10: 5 | N10: 16 | O10: 0.3 | P10: 17 | R10: 5 | S10: 18 | T10: 0.35 | U10: 18 | W10: 5 | X10: 20 | Y10: 0.35 | Z10: 20
A11: 10 | B11: 22 | C11: 0.25 | D11: 15 | H11: 10 | I11: 22 | J11: 0.3 | K11: 17 | M11: 10 | N11: 18 | O11: 0.3 | P11: 17 | R11: 10 | S11: 20 | T11: 0.35 | U11: 18 | W11: 10 | X11: 22 | Y11: 0.35 | Z11: 20
A12: 15 | B12: 24 | C12: 0.25 | D12: 15 | H12: 15 | I12: 24 | J12: 0.3 | K12: 17 | M12: 15 | N12: 20 | O12: 0.3 | P12: 17 | R12: 15 | S12: 22 | T12: 0.35 | U12: 18 | W12: 15 | X12: 22 | Y12: 0.35 | Z12: 20
A13: 20 | B13: 26 | C13: 0.25 | D13: 15 | H13: 20 | I13: 26 | J13: 0.3 | K13: 17 | M13: 20 | N13: 22 | O13: 0.3 | P13: 17 | R13: 20 | S13: 22 | T13: 0.35 | U13: 18 | W13: 20 | X13: 22 | Y13: 0.35 | Z13: 20
A14: 25 | B14: 28 | C14: 0.25 | D14: 15 | H14: 25 | I14: 28 | J14: 0.3 | K14: 17 | M14: 25 | N14: 22 | O14: 0.3 | P14: 17 | R14: 25 | S14: 22 | T14: 0.35 | U14: 18 | W14: 25 | X14: 22 | Y14: 0.35 | Z14: 20
A15: 30 | B15: 30 | C15: 0.25 | D15: 15 | H15: 30 | I15: 30 | J15: 0.3 | K15: 17
A16: 35 | B16: 32 | C16: 0.25 | D16: 15 | H16: 35 | I16: 32 | J16: 0.3 | K16: 17
A19: Factor de Integracion | H19: Factor de Integracion | M19: Factor de Integracion | R19: Factor de Integracion | W19: Factor de Integracion
C20: 365 | J20: 365 | O20: 365 | T20: 365 | Y20: 365
A21: 1 | B21: =+(B6*C6)+D6+365 -> 383 | C21: =+B21/$C$20 -> 1.0493151 | D21: 313 | E21: =+C21*D21 -> 328.43562 | F21: 82.8 | G21: =+E21+F21 -> 411.23562 | H21: 1 | I21: =+(I6*J6)+K6+365 -> 385.6 | J21: =+I21/$C$20 -> 1.0564384 | M21: 1 | N21: =+(N6*O6)+P6+365 -> 384.4 | O21: =+N21/$O$20 -> 1.0531507 | P21: 313 | Q21: =+O21*P21+82.8 -> 412.43616 | R21: 1 | S21: =+(S6*T6)+U6+365 -> 386.5 | T21: =+S21/$T$20 -> 1.0589041 | W21: 1 | X21: =+(X6*Y6)+Z6+365 -> 389.2 | Y21: =+X21/$Y$20 -> 1.0663014
A22: 2 | B22: =+(B7*C7)+D7+365 -> 383.5 | C22: =+B22/$C$20 -> 1.0506849 | D22: 483 | E22: =+C22*D22 -> 507.48082 | F22: 83.38 | G22: =+E22+F22 -> 590.86082 | H22: 2 | I22: =+(I7*J7)+K7+365 -> 386.2 | J22: =+I22/$C$20 -> 1.0580822 | M22: 2 | N22: =+(N7*O7)+P7+365 -> 385 | O22: =+N22/$O$20 -> 1.0547945 | P22: 313 | Q22: =+O22*P22+82.8 -> 412.95068 | R22: 2 | S22: =+(S7*T7)+U7+365 -> 387.2 | T22: =+S22/$T$20 -> 1.0608219 | W22: 2 | X22: =+(X7*Y7)+Z7+365 -> 389.9 | Y22: =+X22/$Y$20 -> 1.0682192
A23: 3 | B23: =+(B8*C8)+D8+365 -> 384 | C23: =+B23/$C$20 -> 1.0520548 | H23: 3 | I23: =+(I8*J8)+K8+365 -> 386.8 | J23: =+I23/$C$20 -> 1.059726 | M23: 3 | N23: =+(N8*O8)+P8+365 -> 385.6 | O23: =+N23/$O$20 -> 1.0564384 | R23: 3 | S23: =+(S8*T8)+U8+365 -> 387.9 | T23: =+S23/$T$20 -> 1.0627397 | W23: 3 | X23: =+(X8*Y8)+Z8+365 -> 390.6 | Y23: =+X23/$Y$20 -> 1.070137
A24: 4 | B24: =+(B9*C9)+D9+365 -> 384.5 | C24: =+B24/$C$20 -> 1.0534247 | H24: 4 | I24: =+(I9*J9)+K9+365 -> 387.4 | J24: =+I24/$C$20 -> 1.0613699 | M24: 4 | N24: =+(N9*O9)+P9+365 -> 386.2 | O24: =+N24/$O$20 -> 1.0580822 | R24: 4 | S24: =+(S9*T9)+U9+365 -> 388.6 | T24: =+S24/$T$20 -> 1.0646575 | W24: 4 | X24: =+(X9*Y9)+Z9+365 -> 391.3 | Y24: =+X24/$Y$20 -> 1.0720548
A25: 5 | B25: =+(B10*C10)+D10+365 -> 385 | C25: =+B25/$C$20 -> 1.0547945 | H25: 5 | I25: =+(I10*J10)+K10+365 -> 388 | J25: =+I25/$C$20 -> 1.0630137 | M25: 5 | N25: =+(N10*O10)+P10+365 -> 386.8 | O25: =+N25/$O$20 -> 1.059726 | R25: 5 | S25: =+(S10*T10)+U10+365 -> 389.3 | T25: =+S25/$T$20 -> 1.0665753 | W25: 5 | X25: =+(X10*Y10)+Z10+365 -> 392 | Y25: =+X25/$Y$20 -> 1.0739726
A26: 10 | B26: =+(B11*C11)+D11+365 -> 385.5 | C26: =+B26/$C$20 -> 1.0561644 | H26: 10 | I26: =+(I11*J11)+K11+365 -> 388.6 | J26: =+I26/$C$20 -> 1.0646575 | M26: 10 | N26: =+(N11*O11)+P11+365 -> 387.4 | O26: =+N26/$O$20 -> 1.0613699 | R26: 10 | S26: =+(S11*T11)+U11+365 -> 390 | T26: =+S26/$T$20 -> 1.0684932 | W26: 10 | X26: =+(X11*Y11)+Z11+365 -> 392.7 | Y26: =+X26/$Y$20 -> 1.0758904
A27: 15 | B27: =+(B12*C12)+D12+365 -> 386 | C27: =+B27/$C$20 -> 1.0575342 | H27: 15 | I27: =+(I12*J12)+K12+365 -> 389.2 | J27: =+I27/$C$20 -> 1.0663014 | M27: 15 | N27: =+(N12*O12)+P12+365 -> 388 | O27: =+N27/$O$20 -> 1.0630137 | R27: 15 | S27: =+(S12*T12)+U12+365 -> 390.7 | T27: =+S27/$T$20 -> 1.070411 | W27: 15 | X27: =+(X12*Y12)+Z12+365 -> 392.7 | Y27: =+X27/$Y$20 -> 1.0758904
A28: 20 | B28: =+(B13*C13)+D13+365 -> 386.5 | C28: =+B28/$C$20 -> 1.0589041 | H28: 20 | I28: =+(I13*J13)+K13+365 -> 389.8 | J28: =+I28/$C$20 -> 1.0679452 | M28: 20 | N28: =+(N13*O13)+P13+365 -> 388.6 | O28: =+N28/$O$20 -> 1.0646575 | R28: 20 | S28: =+(S13*T13)+U13+365 -> 390.7 | T28: =+S28/$T$20 -> 1.070411 | W28: 20 | X28: =+(X13*Y13)+Z13+365 -> 392.7 | Y28: =+X28/$Y$20 -> 1.0758904
A29: 25 | B29: =+(B14*C14)+D14+365 -> 387 | C29: =+B29/$C$20 -> 1.060274 | H29: 25 | I29: =+(I14*J14)+K14+365 -> 390.4 | J29: =+I29/$C$20 -> 1.069589 | M29: 25 | N29: =+(N14*O14)+P14+365 -> 388.6 | O29: =+N29/$O$20 -> 1.0646575 | R29: 25 | S29: =+(S14*T14)+U14+365 -> 390.7 | T29: =+S29/$T$20 -> 1.070411 | W29: 25 | X29: =+(X14*Y14)+Z14+365 -> 392.7 | Y29: =+X29/$Y$20 -> 1.0758904
A30: 30 | B30: =+(B15*C15)+D15+365 -> 387.5 | C30: =+B30/$C$20 -> 1.0616438 | H30: 30 | I30: =+(I15*J15)+K15+365 -> 391 | J30: =+I30/$C$20 -> 1.0712329
A31: 35 | B31: =+(B16*C16)+D16+365 -> 388 | C31: =+B31/$C$20 -> 1.0630137 | H31: 35 | I31: =+(I16*J16)+K16+365 -> 391.6 | J31: =+I31/$C$20 -> 1.0728767

Sheet Calculo
C4: CALCULO SALARIO A EMPLEADO
C5: 2026
C8: Periodo de Nómina
C9: Días de Pago | D9: 14 | K9: 7 | L9: 14 | M9: 15 | N9: 30
C10: Días Naturales | D10: 14
C11: Domingos | D11: 0
C13: Salarios Mínimos Vigentes | P13: 1978 | Q13: 100
C14: Area Geográfica de Empresa | D14: 419.88 | P14: 2324.24 | Q14: =+P14*Q13/P13 -> 117.50455
C15: Distrito Federal | D15: 315.04 | Q15: =+Q13-Q14 -> -17.50455
C16: UMA | D16: =+'IMSS Calculo'!E2 -> 117.31 | E16: ESTIMACION de INCREMENTO del 10%
E17: LA UMA YA ESTA ACTUALIZADA A 2025 (REAL)
C18: Datos de Empleado
C19: Salario Diario | D19: 752.4459 | E19: =+D19*30.4 -> 22874.355
C20: Salario Diario Integrado | D20: =+J39 -> 789.55282 | E20: =+D19/2 -> 376.22295
C21: Años de Antigüedad en fecha de Baja | D21: 0
C22: Crédito Infonavit | D22: No Tiene
C23: Valor de Crédito | D23: 0
C24: Días de Bimestre | D24: 61
C26: Acumulados Mensuales para Ajuste | F26: 6647643937
C27: Posición del Periodo en el Mes | D27: 1
C28: 521 - Suma de Percepciones Periódicas | D28: 0
C29: 522 - Suma de Exentos Periódicos | D29: 0
C30: 523 - ISR Antes de Subsidio | D30: 0
C31: 524 - Subsidio al Empleo Acreditado | D31: 0
B34: # | C34: Concepto | D34: Percepción | E34: Exento
B35: 1 | C35: Sueldo Ordinario | D35: =+D19*12 -> 9029.3508
B36: 2 | C36: Séptimo Día | D36: =+D19*2 -> 1504.8918 | I36: SDI
B37: 3 | C37: Horas Extras Dobles | D37: 0 | E37: =MIN(( D37+D39+D40)/2, 5*$D$16) -> 0 | I37: Salario Diario | J37: =+D19 -> 752.4459
B38: 4 | C38: Horas Extras Triples | D38: 0 | I38: Factor Integracion | J38: =+Tablas!C21 -> 1.0493151
B39: 5 | C39: Festivo Trabajado | D39: 0 | I39: SDI | J39: =+J37*J38 -> 789.55282
B40: 6 | C40: Descanso Trabajado | D40: 0 | E40: 0
B41: 7 | C41: Prima Dominical | D41: 0 | E41: =+D41 -> 0 | I41: Variables | J41: 0
B42: 11 | C42: Ajuste de Faltas | D42: 0
B43: 21 | C43: Vacaciones | D43: 0 | F43: Exento Anual | G43: Por 14 dias | I43: Total SDI | J43: =+J39+J41 -> 789.55282
B44: 22 | C44: Prima Vacacional | D44: =+(D19*24)*0.25/12/2.17 -> 173.37463 | E44: 67.493425 | F44: 1759.65 | G44: =+F44/365*14 -> 67.493425
B45: 23 | C45: Aguinaldo | D45: =(D19*30/12)/2.17 -> 866.87316 | E45: 134.98685 | F45: =+D16*30 -> 3519.3 | G45: =+F45/365*14 -> 134.98685
B46: 24 | C46: Reparto de Utilidades (PTU) | D46: 1520.58 | E46: 67.493425 | F46: =+D16*15 -> 1759.65 | G46: =+F46/365*14 -> 67.493425
B47: 31 | C47: Bono fondo de ahorro | D47: =+D19*0.0500329*D9 -> 527.05871
B48: 32 | C48: Bono vale de despesa | D48: =+D47 -> 527.05871
A49: 90 | B49: 34 | C49: Internet | D49: 138.25
B50: 39 | C50: Bono Navideño | D50: 17.28
C51: Bono de desempeño mensual | D51: =+E19/2.17 -> 10541.178 | E51: 0
B52: 91 | C52: Gratificación por Separación | D52: 0
B53: 92 | C53: Indemnización | D53: 0
B54: 93 | C54: Prima de Antigüedad | D54: 0 | E54: =MIN($D$72*1, 90*$D$14*ROUND($D$21,0)) -> 0
C55: Total de Percepciones: | D55: =SUM(D35:D54) -> 24845.895 | E55: =SUM(E35:E54) -> 269.9737 | I55: Dias Periodo Mensual | J55: 30.4
C57: Deducciones | I57: IMSS Patronal | J57: =+I79 -> 1176.193
B58: 101 | C58: ISR (ISPT) | D58: =MAX( G73-H73, 0 ) + G71 +G72 -> 4558.86 | E58: Neto de ISR Periódico y SUBE + ISR de Anuales y Separación
B59: 103 | C59: Subsidio al Empleo | D59: =MIN(G73-H73,0) -> 0 | E59: Neto de ISR Periódico y SUBE | I59: Infonavit | J59: =+I81 -> 552.68697
B60: 134 | C60: Crédito INFONAVIT | D60: 0
B61: 135 | C61: IMSS Trabajador | D61: =+'IMSS Calculo'!D54 -> 287.03319 | I61: RCV | J61: =+I83 -> 1051.5422
C62: Total Semanal | D62: =SUM(D58:D61) -> 4845.8932
I63: Impuesto Estatal | J63: =+D236 -> 1137.942
C64: Sodexo | D64: 0
J66: =SUM(J57:J64) -> 3918.3643
C67: Salario NETO Semanal | D67: =+D55-D62+D64 -> 20000.002 | E67: 20000 | F67: =+D67-E67 -> 0.0021954392
D70: Percepciones | E70: Exento | F70: Gravado | G70: ISR | H70: SUBE
C71: Percepciones Anuales (Art. 142 RISR) | D71: =D43+D44+D45+D46 -> 2560.8278 | E71: =E41+E44+E45+E46 -> 269.9737 | F71: =D71-E71 -> 2290.8541 | G71: 0
C72: Pagos por Separación | D72: =D52+D53+D54 -> 0 | E72: =E54 -> 0 | F72: =D72-E72 -> 0 | G72: =D168 -> 0
C73: Percepciones Periódicas | D73: =D55-D71-D72 -> 22285.068 | E73: =E55-E71-E72 -> 0 | F73: =D73-E73 -> 22285.068 | G73: =D95 -> 4558.86 | H73: =+D106 -> 0
C74: Acumulado Mensual | D74: =D28 -> 0 | E74: =D29 -> 0 | F74: =D74-E74 -> 0
C75: Suma Periódicas + Acumulado | D75: =D73+D74 -> 22285.068 | E75: =+E71 -> 269.9737 | F75: =D75-E75 -> 22015.094
C78: ISR de Percepciones Periódicas | H78: IMPUESTOS PATRONALES
C79: Percepciones Gravadas | D79: =+D55-E55 -> 24575.922 | H79: IMSS Patronal | I79: =+'IMSS Calculo'!E54 -> 1176.193
C80: ( / ) Días de Periodo de Pago | D80: =$D$9*$D$27 -> 14
C81: (X) Factor Mensual | D81: =$J$55 -> 30.4 | H81: Infonavit | I81: =+D231 -> 552.68697
C82: (=) Gravadas Promedio Mensual | D82: =ROUND(D79/D80*D81,2) -> 53364.86
C83: Tabla Art. 113 LISR | H83: RCV | I83: =+'IMSS Calculo'!E56 -> 1051.5422
C84: (-) Límite Inferior | D84: =VLOOKUP($D$82,$D$174:$G$184,1) -> 35362.84
C85: (=) Excedente | D85: =D82-D84 -> 18002.02 | H85: Impuesto Estatal | I85: =+D236 -> 1137.942
C86: (X) Tasa | D86: =VLOOKUP($D$82,$D$174:$G$184,4) -> 0.2352
C87: (=) Impuesto Marginal | D87: =D85*D86 -> 4234.0751 | I87: =SUM(I79:I85) -> 3918.3643
C88: (+) Cuota Fija | D88: =VLOOKUP($D$82,$D$174:$G$184,3) -> 5665.16
C89: (=) ISR Promedio Mensual | D89: =D87+D88 -> 9899.2351
C91: (/ ) Factor Mensual | D91: =$J$55 -> 30.4
C92: (X) Días de Periodo de Pago | D92: =$D$9*$D$27 -> 14
C93: (=) ISR de Periodo | D93: =ROUND(D89/D91*D92,2) -> 4558.86
C94: (-) Acumulado Mensual ISR (523) | D94: =D30 -> 0
C95: (=) ISR Ajustado | D95: =D93-D94 -> 4558.86
C97: Subsidio al Empleo
C98: Gravadas Promedio Mensual | D98: =D82 -> 53364.86
C100: Tabla Subsidio al Empleo | D100: =IF( D98 <= 0, 0, VLOOKUP(D98,$D$188:$F$198,3)) -> 0
C102: (/) Factor Mensual | D102: =$J$55 -> 30.4
C103: (X) Días de Periodo de Pago | D103: =$D$9*$D$27 -> 14
C104: (=) Subsidio del Periodo | D104: =ROUND(D100/D102*D103,2) -> 0
C105: (-) Acumulado de Subsidio (524) | D105: =D31 -> 0
C106: (=) Subsidio Ajustado | D106: =D104-D105 -> 0
C109: ISR de Anuales (Art. 142 RISR)
C110: Un Salario Mensual | D110: =IF( D119<=0, 0, ROUND($D$19*$J$55,2)) -> 22874.36
C111: Tabla Art. 113 LISR
C112: (-) Límite Inferior | D112: =VLOOKUP($D$110,$D$174:$G$181,1) -> 17533.65
C113: (=) Excedente | D113: =D110-D112 -> 5340.71
C114: (X) Tasa | D114: =VLOOKUP($D$110,$D$174:$G$181,4) -> 0.2136
C115: (=) Impuesto Marginal | D115: =D113*D114 -> 1140.7757
C116: (+) Cuota Fija | D116: =VLOOKUP($D$110,$D$174:$G$181,3) -> 1856.84
C117: (=) ISR de Un Salario Mensual | D117: =D115+D116 -> 2997.6157 | E117: Impuesto "A"
C119: Percepciones Anuales Gravadas | D119: =F71 -> 2290.8541
C120: (/) Factor Anual | D120: 365
C121: (X) Factor Mensual | D121: =$J$55 -> 30.4
C122: (=) Anuales Mensualizadas | D122: =ROUND(D119/D120*D121,2) -> 190.8
...

Sheet Hoja1
A1: 2016 | B1: 73.04
A2: 2017 | B2: 75.49 | C2: =+B2-B1 -> 2.45
A3: 2018 | B3: 80.6 | C3: =+B3-B2 -> 5.11
A4: 2019 | B4: 84.49 | C4: =+B4-B3 -> 3.89
A5: 2020 | B5: 86.88 | C5: =+B5-B4 -> 2.39
A6: 2021 | B6: 89.62 | C6: =+B6-B5 -> 2.74
A7: 2022 | B7: 96.22 | C7: =+B7-B6 -> 6.6
A8: 2023 | B8: 103.74 | C8: =+B8-B7 -> 7.52

Sheet IMSS Calculo
E1: UMA
C2: IMSS Empleado | E2: 117.31 | G2: NUEVO TOPE SALARIAL
C3: Salario Base de Cotizacion | D3: =+Calculo!D20 -> 789.55282 | E3: =+D3 -> 789.55282 | G3: =+E2*25 -> 2932.75 | N3: Monto UMA | S3: Salario Minimo
C4: (X) Tasa Art. 25 | D4: 0.0025 | E4: 0.007 | N4: Enero | O4: 2021 | P4: 89.62 | S4: Enero | T4: 2020 | U4: 213.39
C5: (=) Prestaciones en Dinero | D5: =+D3*D4 -> 1.9738821 | E5: =+E3*E4 -> 5.5268697 | N5: Enero | O5: 2021 A | P5: 95.28 | S5: Enero | T5: 2019 | U5: 84.49
S6: Enero | T6: 2019 | U6: 84.49
C7: Salario Base de Cotizacion | D7: =+$D$3 -> 789.55282 | E7: =+E3 -> 789.55282 | S7: Enero | T7: 2018 | U7: 88.36
C8: (-) 3 UMA | D8: =+E2*3 -> 351.93 | E8: =+E2*3 -> 351.93 | S8: Enero | T8: 2017 | U8: 80.04
C9: (=) Excedente | D9: =+D7-D8 -> 437.62282 | E9: =+E7-E8 -> 437.62282
C10: (X) Tasa Art. 106-2 | D10: 0.004 | E10: 0.011 | L10: UMA PROYECTADA | M10: 117.31
C11: (=)Cuota Diaria Art. 106-2 (E y M) | D11: =+D9*D10 -> 1.7504913 | E11: =+E9*E10 -> 4.813851
H12: Tabla de % para calculos de retiro, cesantia y vejes en edad avanzada
C13: Salario Base de Cotizacion | D13: =+$D$7 -> 789.55282 | E13: =+E3 -> 789.55282
C14: (X) Tasa Art 107 | D14: 0.00375 | E14: 0.0105 | H14: Limite inferior | I14: Limite superior | J14: Limite inferior salarios | K14: Limite superio salario | L14: Limite inferior salarios | M14: Limite superio salario | N14: Porcentaje aplicable
C15: (=) Pensionados y Beneficiarios Art. 107 (E y M) | D15: =+D13*D14 -> 2.9608231 | E15: =+E13*E14 -> 8.2903046 | H15: 0 | I15: 1 | J15: 0 | K15: 315.04 | L15: 0 | M15: 440.87 | N15: 0.0315
H16: 1.01 | I16: 1.5 | J16: 318.1904 | K16: 175.965 | L16: 445.2787 | M16: 175.965 | N16: 0.03676
C17: Salario Base de Cotizacion | D17: =+$D$3 -> 789.55282 | E17: =+E3 -> 789.55282 | H17: 1.51 | I17: 2 | J17: 177.1381 | K17: 234.62 | L17: 177.1381 | M17: 234.62 | N17: 0.04851
C18: (X) Tasa Invalidez y Vida | D18: 0.00625 | E18: 0.0175 | H18: 2.01 | I18: 2.5 | J18: 235.7931 | K18: 293.275 | L18: 235.7931 | M18: 293.275 | N18: 0.05556
C19: (=) Cuota Diaria Invalidez y Vida | D19: =+D17*D18 -> 4.9347051 | E19: =+E17*E18 -> 13.817174 | H19: 2.51 | I19: 3 | J19: 294.4481 | K19: 351.93 | L19: 294.4481 | M19: 351.93 | N19: 0.06026
H20: 3.01 | I20: 3.5 | J20: 353.1031 | K20: 410.585 | L20: 353.1031 | M20: 410.585 | N20: 0.06361
C21: Salario Base de Cotizacion | D21: =+$D$3 -> 789.55282 | E21: =+E3 -> 789.55282 | H21: 3.51 | I21: 4 | J21: 411.7581 | K21: 469.24 | L21: 411.7581 | M21: 469.24 | N21: 0.06613
C22: (X) Tasa Cesantia y Vejez | D22: 0.01125 | E22: 0.02 | H22: 4.01 | I22: En adelante | J22: 470.4131 | K22: 2932.75 | L22: 470.4131 | M22: 2932.75 | N22: 0.07513
C23: (=) Cuota Diaria Cesantia y Vejez | D23: =+D21*D22 -> 8.8824692 | E23: =+E21*E22 -> 15.791056
I24: NOTA:
C25: Salario Base de Cotizacion | E25: =+E3 -> 789.55282
C26: (X) Tasa Cesantia y Vejez | E26: =VLOOKUP(E25,$L$15:$N$22,3) -> 0.07513
C27: (=) Cuota Diaria Cesantia y Vejez | E27: =+E25*E26 -> 59.319103 | I27: El primer renglon y el 1.01 estan en VSM
I28: Del 1.5 al 4.01 son UMAS
C29: Salario Base de Cotizacion | E29: =+E3 -> 789.55282 | I29: y el limite superior en salario es el tope de 25 UMAS
C30: (X) Guarderias y Prestaciones | E30: 0.01
C31: (=) Guarderia y Prestaciones | D31: 0 | E31: =+E29*E30 -> 7.8955282
C33: Salario Minimo Gral | E33: =+E2 -> 117.31
C34: Cuota Fija | E34: 0.204
C35: (=) Cuota Fija Enfermedad y Mater Empresa | D35: 0 | E35: =+E33*E34 -> 23.93124
C37: Salario Base de Cotizacion | E37: =+E3 -> 789.55282
C38: (X) Prima de Riesgo | E38: 0.025 | G38: 0.5
C39: (=) Monto Prima de Riesgo | D39: 0 | E39: =+E37*E38 -> 19.738821
C43: Prestaciones Dinero Art. 25 | D43: =+D5 -> 1.9738821 | E43: =+E5 -> 5.5268697
C44: (=) Enfermedad Y Mat 106-2 | D44: =+D11 -> 1.7504913 | E44: =+E11 -> 4.813851
C45: (=) Pensionados y Benefic Art. 107 | D45: =+D15 -> 2.9608231 | E45: =+E15 -> 8.2903046
C46: (+) Cuota Invalidez y Vida | D46: =+D19 -> 4.9347051 | E46: =+E19 -> 13.817174
C47: (+) Cuota Cesantia y Vejez | D47: =+D23 -> 8.8824692 | E47: 0
C48: (=) Cuota Fija Enfermedad y Maternidad | D48: =+D35 -> 0 | E48: =+E35 -> 23.93124
C49: (+) Guarderias Prestacion | D49: 0 | E49: =+E31 -> 7.8955282
C50: (=) Prima de Riesgo Patronal | D50: 0 | E50: =+E39 -> 19.738821
C51: (=) Cuota Diara Empleado | D51: =SUM(D43:D50) -> 20.502371 | E51: =SUM(E43:E50) -> 84.013789
C53: (X) Dias de Periodo | D53: =+Calculo!D9 -> 14 | E53: =+D53 -> 14
C54: (=) IMSS Empleado | D54: =+D51*D53 -> 287.03319 | E54: =+E51*E53 -> 1176.193
C56: RCV Patronal | E56: =(E23+E27)*14 -> 1051.5422

Sheet Simulacion
B3: SIMULACION SALARIO
B5: Percepcion:
C6: Sueldo Ordinario | D6: =+Calculo!D35 -> 9029.3508
C7: Septimo Dia | D7: =+Calculo!D36 -> 1504.8918
C8: =+Calculo!C44 -> Prima Vacacional | D8: =+Calculo!D44 -> 173.37463
C9: =+Calculo!C45 -> Aguinaldo | D9: =+Calculo!D45 -> 866.87316
C10: =+Calculo!C46 -> Reparto de Utilidades (PTU) | D10: =+Calculo!D46 -> 1520.58
C11: =+Calculo!C47 -> Bono fondo de ahorro | D11: =+Calculo!D47 -> 527.05871
C12: =+Calculo!C48 -> Bono vale de despesa | D12: =+Calculo!D48 -> 527.05871
C13: =+Calculo!C49 -> Internet | D13: =+Calculo!D49 -> 138.25
C14: =+Calculo!C50 -> Bono Navideño | D14: =+Calculo!D50 -> 17.28
C15: =+Calculo!C51 -> Bono de desempeño mensual | D15: =+Calculo!D51 -> 10541.178
C16: Total Percepcion | D16: =SUM(D6:D15) -> 24845.895
B18: Deduccion:
C19: IMSS Trabajador | D19: =+Calculo!D61 -> 287.03319
C20: ISPT Trabajador | D20: =+Calculo!D58 -> 4558.86
C21: Ajuste Moneda | D21: 0
C22: Total Deducciones | D22: =SUM(D19:D21) -> 4845.8932
C25: Neto a Pagar | D25: =+D16-D22 -> 20000.002
C26: Sodexo | D26: =+Calculo!D64 -> 0
C27: Neto + Sodexo | D27: =+D25+D26 -> 20000.002
B28: Impuesto Patronal
C29: IMSS Empresa | D29: =+Calculo!I79 -> 1176.193
C30: Infonavit | D30: =+Calculo!I81 -> 552.68697
C31: RCV | D31: =+Calculo!I83 -> 1051.5422
C32: Impuesto Estatal | D32: =+Calculo!I85 -> 1137.942
C33: Total Patronales | D33: =SUM(D29:D32) -> 3918.3643
C35: Costo nomina | D35: =+D16+D33+D26 -> 28764.26
C37: provision de FQ | D37: =+(((12*D7)*0.25)+(12*D7)+(15*D7))/52 -> 868.20681
A39: Comedor | D39: 0
B41: Precio | C41: Meses
A42: Glucometro | B42: 8.23 | C42: 1 | D42: =+B42*1.15 -> 9.4645
A43: Cubrebocas | B43: 4.21 | C43: 1 | D43: =+B43*1.15 -> 4.8415
A44: Total | D44: =SUM(D42:D43) -> 14.306
A46: Jornada | D46: 48
A47: Utilidad | D47: 500
A50: OVH | D50: 12.8
A51: Variables | D51: 0.93
A52: Utilidad | D52: =+D47/D46 -> 10.416667
A53: Costo Hra | D53: =+D35/D46 -> 599.25541
A54: Costos EPP | D54: =+D44/D46 -> 0.29804167
A55: Provision de FQ | D55: =+D37/D46 -> 18.087642
A56: Comedor | D56: =+D39/D46 -> 0
A57: Costo Hra Cliente | D57: =SUM(D50:D56) -> 641.78776

Sheet Simulacion completa
A1: CARLOS ALBERTO CANTU BARRON | F1: MASIEL MURRIETA VALDEZ | K1: JESUS ALBERTO SOTO MORA | P1: JESUS ALBERTO MORENO CORDOVA | U1: JORGE GUTIERREZ | Z1: DITHER ROSAS | AE1: JUAN CARLOS MENDOZA | AJ1: IVAN SALAZAR | AO1: Rosario Moreno | AU1: Generica 1 | AZ1: Generica 2 | BH1: Santander Bank USA | BI1: 45903 | BO1: Generica 1 | BT1: Generica 2
AO2: Paquete incremento 10% | AP2: P | AV2: P | BA2: P | BI2: 18.7494 | BP2: P | BU2: P
A3: SIMULACION SALARIO (Bi-Weekly Payroll FULL) | F3: SIMULACION SALARIO (Bi-Weekly Payroll FULL) | K3: SIMULACION SALARIO (Bi-Weekly Payroll FULL) | P3: SIMULACION SALARIO (Bi-Weekly Payroll FULL) | U3: SIMULACION SALARIO (Bi-Weekly Payroll FULL) | Z3: SIMULACION SALARIO (Bi-Weekly Payroll FULL) | AE3: SIMULACION SALARIO (Bi-Weekly Payroll FULL) | AJ3: SIMULACION SALARIO (Bi-Weekly Payroll FULL) | AO3: SIMULACION SALARIO (Bi-Weekly Payroll FULL) | AU3: SIMULACION SALARIO (Bi-Weekly Payroll FULL) $50K NET + BENEFITS | AZ3: SIMULACION SALARIO (Bi-Weekly Payroll FULL) $40K NET + BENEFITS | BF3: Bi-Weekly Gross Total (Fully Loaded) MXN | BG3: Bi-Weekly Service Fee MXN | BH3: Total Bi-Weekly Invoice MXN | BI3: Total Bi-Weekly Invoice USD* | BK3: NET PAY | BO3: SIMULACION SALARIO (Bi-Weekly Payroll FULL) $50K NET (INCLUDING BENEFITS) | BT3: SIMULACION SALARIO (Bi-Weekly Payroll FULL) $40K (UNCLUDING BENEFITS)
BE4: =+A1 -> CARLOS ALBERTO CANTU BARRON | BF4: =+C53 -> 103634.86 | BG4: =BF4*S54 -> 11399.834 | BH4: =+BG4+BF4 -> 115034.69 | BI4: =BH4/$BI$2 -> 6135.3799 | BK4: =+C25 -> 60832.895
A5: Percepcion (Gross Income): | C5: Weekly | D5: Monthly Reference | F5: Percepcion (Gross Income): | I5: Monthly Reference | K5: Percepcion (Gross Income): | N5: Monthly Reference | P5: Percepcion (Gross Income): | S5: Monthly Reference | U5: Percepcion (Gross Income): | W5: Actual | X5: Monthly Reference | Z5: Percepcion (Gross Income): | AB5: Actual | AC5: Monthly Reference | AE5: Percepcion (Gross Income): | AH5: Monthly Reference | AJ5: Percepcion (Gross Income): | AM5: Monthly Reference | AO5: Percepcion (Gross Income): | AR5: Monthly Reference | AU5: Percepcion (Gross Income): | AX5: Monthly Reference | AZ5: Percepcion (Gross Income): | BC5: Monthly Reference | BE5: =+F1 -> MASIEL MURRIETA VALDEZ | BF5: =+H53 -> 64336.879 | BG5: =+BF5*S54 -> 7077.0567 | BH5: =+BG5+BF5 -> 71413.936 | BI5: =BH5/$BI$2 -> 3808.8652 | BK5: =+H25 -> 37386.431 | BO5: Percepcion (Gross Income): | BR5: Monthly Reference | BT5: Percepcion (Gross Income): | BW5: Monthly Reference
B6: Sueldo Ordinario (Salary) | C6: 51600 | D6: =((C6+C7)/2)*4.33 -> 130333 | G6: Sueldo Ordinario (Salary) | H6: 30000 | I6: =((H6+H7)/2)*4.33 -> 75775 | L6: Sueldo Ordinario (Salary) | M6: 32136 | N6: =((M6+M7)/2)*4.33 -> 81170.18 | Q6: Sueldo Ordinario (Salary) | R6: 105600 | S6: =((R6+R7)/2)*4.33 -> 266728 | V6: Sueldo Ordinario (Salary) | W6: 21989.28 | X6: =((W6+W7)/2)*4.33 -> 55541.256 | AA6: Sueldo Ordinario (Salary) | AB6: 25181.04 | AC6: =((AB6+AB7)/2)*4.33 -> 63603.11 | AF6: Sueldo Ordinario (Salary) | AG6: 21600 | AH6: =((AG6+AG7)/2)*4.33 -> 54558 | AK6: Sueldo Ordinario (Salary) | AL6: 29092.08 | AM6: =((AL6+AL7)/2)*4.33 -> 73481.745 | AP6: Sueldo Ordinario (Salary) | AQ6: 38129.4 | AR6: =((AQ6+AQ7)/2)*4.33 -> 96308.509 | AV6: Sueldo Ordinario (Salary) | AW6: 28126.658 | AX6: =((AW6+AW7)/2)*4.33 -> 71043.251 | BA6: Sueldo Ordinario (Salary) | BB6: 21782.016 | BC6: =((BB6+BB7)/2)*4.33 -> 55017.742 | BE6: =+K1 -> JESUS ALBERTO SOTO MORA | BF6: =+M53 -> 69380.162 | BG6: =+BF6*S54 -> 7631.8178 | BH6: =+BG6+BF6 -> 77011.98 | BI6: =BH6/$BI$2 -> 4107.437 | BK6: =+M25 -> 39684.468 | BP6: Sueldo Ordinario (Salary) | BQ6: 11826.439 | BR6: =((BQ6+BQ7)/2)*4.33 -> 29871.614 | BU6: Sueldo Ordinario (Salary) | BV6: 9029.3508 | BW6: =((BV6+BV7)/2)*4.33 -> 22806.635
B7: Septimo Dia (Seventh Day) | C7: 8600 | G7: Septimo Dia (Seventh Day) | H7: 5000 | L7: Septimo Dia (Seventh Day) | M7: 5356 | Q7: Septimo Dia (Seventh Day) | R7: 17600 | V7: Septimo Dia (Seventh Day) | W7: 3664.88 | AA7: Septimo Dia (Seventh Day) | AB7: 4196.84 | AF7: Septimo Dia (Seventh Day) | AG7: 3600 | AK7: Septimo Dia (Seventh Day) | AL7: 4848.68 | AP7: Septimo Dia (Seventh Day) | AQ7: 6354.9 | AV7: Septimo Dia (Seventh Day) | AW7: 4687.7764 | BA7: Septimo Dia (Seventh Day) | BB7: 3630.336 | BE7: =+P1 -> JESUS ALBERTO MORENO CORDOVA | BF7: =+R53 -> 222149.52 | BG7: =+BF7*S54 -> 24436.447 | BH7: =+BG7+BF7 -> 246585.97 | BI7: =BH7/$BI$2 -> 13151.672 | BK7: =+R25 -> 133142.75 | BP7: Septimo Dia (Seventh Day) | BQ7: 1971.0732 | BU7: Septimo Dia (Seventh Day) | BV7: 1504.8918
B8: Bono Fondo de Ahorro (5% Savings Fund) | C8: 3011.98 | D8: =(C8/2)*4.33 -> 6520.9367 | G8: Bono Fondo de Ahorro (5% Savings Fund) | H8: 1751.15 | I8: =(H8/2)*4.33 -> 3791.2398 | L8: Bono Fondo de Ahorro (5% Savings Fund) | M8: 1875.83 | N8: =(M8/2)*4.33 -> 4061.1719 | Q8: Bono Fondo de Ahorro (5% Savings Fund) | R8: 6164.06 | S8: =(R8/2)*4.33 -> 13345.19 | V8: Bono Fondo de Ahorro (5% Savings Fund) | W8: 1282.708 | X8: =(W8/2)*4.33 -> 2777.0628 | AA8: Bono Fondo de Ahorro (5% Savings Fund) | AB8: 1468.89 | AC8: =(AB8/2)*4.33 -> 3180.1469 | AF8: Bono Fondo de Ahorro (5% Savings Fund) | AG8: 1260 | AH8: =(AG8/2)*4.33 -> 2727.9 | AK8: Bono Fondo de Ahorro (5% Savings Fund) | AL8: 1697.038 | AM8: =(AL8/2)*4.33 -> 3674.0873 | AP8: Bono Fondo de Ahorro (5% Savings Fund) | AQ8: 2224.215 | AR8: =(AQ8/2)*4.33 -> 4815.4255 | AV8: Bono Fondo de Ahorro (5% Savings Fund) | AW8: 1641.8013 | AX8: =(AW8/2)*4.33 -> 3554.4999 | BA8: Bono Fondo de Ahorro (5% Savings Fund) | BB8: 1271.4537 | BC8: =(BB8/2)*4.33 -> 2752.6972 | BE8: =+U1 -> JORGE GUTIERREZ | BF8: =+W53 -> 45534.352 | BG8: =+BF8*X54 -> 5919.4658 | BH8: =+BG8+BF8 -> 51453.818 | BI8: =BH8/$BI$2 -> 2744.2915 | BK8: =+W25 -> 26584.831 | BP8: Bono Fondo de Ahorro (5% Savings Fund) | BQ8: 690.32956 | BR8: =(BQ8/2)*4.33 -> 1494.5635 | BU8: Bono Fondo de Ahorro (5% Savings Fund) | BV8: 527.05871 | BW8: =(BV8/2)*4.33 -> 1141.0821
B9: Bono Vale despensa (5% food Coupons) | C9: 3011.98 | D9: =(C9/2)*4.33 -> 6520.9367 | G9: Bono Vale despensa (5% food Coupons) | H9: 1751.15 | I9: =(H9/2)*4.33 -> 3791.2398 | L9: Bono Vale despensa (5% food Coupons) | M9: 1875.83 | N9: =(M9/2)*4.33 -> 4061.1719 | Q9: Bono Vale despensa (5% food Coupons) | R9: 6164.06 | S9: =(R9/2)*4.33 -> 13345.19 | V9: Bono Vale despensa (5% food Coupons) | W9: 1282.708 | X9: =(W9/2)*4.33 -> 2777.0628 | AA9: Bono Vale despensa (5% food Coupons) | AB9: 1468.89 | AC9: =(AB9/2)*4.33 -> 3180.1469 | AF9: Bono Vale despensa (5% food Coupons) | AG9: 1260 | AH9: =(AG9/2)*4.33 -> 2727.9 | AK9: Bono Vale despensa (5% food Coupons) | AL9: 1697.038 | AM9: =(AL9/2)*4.33 -> 3674.0873 | AP9: Bono Vale despensa (5% food Coupons) | AQ9: 2224.215 | AR9: =(AQ9/2)*4.33 -> 4815.4255 | AV9: Bono Vale despensa (5% food Coupons) | AW9: 1641.8013 | AX9: =(AW9/2)*4.33 -> 3554.4999 | BA9: Bono Vale despensa (5% food Coupons) | BB9: 1271.4537 | BC9: =(BB9/2)*4.33 -> 2752.6972 | BE9: =+Z1 -> DITHER ROSAS | BF9: =+AB53 -> 51443.138 | BG9: =+BF9*AC54 -> 6687.6079 | BH9: =+BG9+BF9 -> 58130.746 | BI9: =BH9/$BI$2 -> 3100.4057 | BK9: =+AB25 -> 29840.001 | BP9: Bono Vale despensa (5% food Coupons) | BQ9: 690.32956 | BR9: =(BQ9/2)*4.33 -> 1494.5635 | BU9: Bono Vale despensa (5% food Coupons) | BV9: 527.05871 | BW9: =(BV9/2)*4.33 -> 1141.0821
B10: Aguinaldo | C10: 4953.92 | D10: =(C10/2)*4.33 -> 10725.237 | G10: Aguinaldo | H10: 2880.18 | I10: =(H10/2)*4.33 -> 6235.5897 | L10: Aguinaldo | M10: 3085.25 | N10: =(M10/2)*4.33 -> 6679.5662 | Q10: Aguinaldo | R10: 10138.25 | S10: =(R10/2)*4.33 -> 21949.311 | V10: Aguinaldo | W10: 2108.5611 | X10: =(W10/2)*4.33 -> 4565.0348 | AA10: Aguinaldo | AB10: 2414.6203 | AC10: =(AB10/2)*4.33 -> 5227.6529 | AF10: Aguinaldo | AG10: 2071.23 | AH10: =(AG10/2)*4.33 -> 4484.213 | AK10: Aguinaldo | AL10: 2789.6515 | AM10: =(AL10/2)*4.33 -> 6039.5955 | AP10: Aguinaldo | AQ10: 3656.2438 | AR10: =(AQ10/2)*4.33 -> 7915.7679 | AV10: Aguinaldo | AW10: 2700.332 | AX10: =(AW10/2)*4.33 -> 5846.2188 | BA10: Aguinaldo | BB10: 2091.2074 | BC10: =(BB10/2)*4.33 -> 4527.464 | BE10: =+AE1 -> JUAN CARLOS MENDOZA | BF10: =+AG53 -> 46171.029 | BG10: =+BF10*AH54 -> 6002.2337 | BH10: =+BG10+BF10 -> 52173.262 | BI10: =BH10/$BI$2 -> 2782.663 | BK10: =+AG25 -> 26187.822 | BP10: Aguinaldo | BQ10: 1135.4108 | BR10: =(BQ10/2)*4.33 -> 2458.1644 | BU10: Aguinaldo | BV10: 866.87316 | BW10: =(BV10/2)*4.33 -> 1876.7804
B11: Bono Internet (Home Office Bonus) | C11: 138.25 | D11: =(C11/2)*4.33 -> 299.31125 | G11: Bono Navideño (Christmas Bonus) | H11: 17.28 | I11: =(H11/2)*4.33 -> 37.4112 | L11: Bono Internet (Home Office Bonus) | M11: 138.25 | N11: =(M11/2)*4.33 -> 299.31125 | Q11: Bono Navideño (Christmas Bonus) | R11: 17.28 | S11: =(R11/2)*4.33 -> 37.4112 | V11: Bono Navideño (Christmas Bonus) | W11: 17.28 | X11: =(W11/2)*4.33 -> 37.4112 | AA11: Bono Navideño (Christmas Bonus) | AB11: 17.28 | AC11: =(AB11/2)*4.33 -> 37.4112 | AF11: Bono Navideño (Christmas Bonus) | AG11: 17.28 | AH11: =(AG11/2)*4.33 -> 37.4112 | AK11: Bono Navideño (Christmas Bonus) | AL11: 17.28 | AM11: =(AL11/2)*4.33 -> 37.4112 | AP11: Bono Navideño (Christmas Bonus) | AQ11: 17.28 | AR11: =(AQ11/2)*4.33 -> 37.4112 | AV11: Bono Navideño (Christmas Bonus) | AW11: 17.28 | AX11: =(AW11/2)*4.33 -> 37.4112 | BA11: Bono Navideño (Christmas Bonus) | BB11: 17.28 | BC11: =(BB11/2)*4.33 -> 37.4112 | BE11: =+AJ1 -> IVAN SALAZAR | BF11: =+AL53 -> 60332.749 | BG11: =+BF11*AM54 -> 7843.2574 | BH11: =+BG11+BF11 -> 68176.007 | BI11: =BH11/$BI$2 -> 3636.17 | BK11: =+AL25 -> 34024.134 | BP11: Bono Navideño (Christmas Bonus) | BQ11: 17.28 | BR11: =(BQ11/2)*4.33 -> 37.4112 | BU11: Bono Navideño (Christmas Bonus) | BV11: 17.28 | BW11: =(BV11/2)*4.33 -> 37.4112
B12: Bono Navideño (Christmas Bonus) | C12: 17.28 | D12: =(C12/2)*4.33 -> 37.4112 | G12: Bono Internet (Home Office Bonus) | H12: 138.25 | I12: =(H12/2)*4.33 -> 299.31125 | L12: Bono Navideño (Christmas Bonus) | M12: 17.28 | N12: =(M12/2)*4.33 -> 37.4112 | Q12: Bono Internet (Home Office Bonus) | R12: 138.25 | S12: =(R12/2)*4.33 -> 299.31125 | V12: Bono Internet (Home Office Bonus) | W12: 138.25 | X12: =(W12/2)*4.33 -> 299.31125 | AA12: Bono Internet (Home Office Bonus) | AB12: 138.25 | AC12: =(AB12/2)*4.33 -> 299.31125 | AF12: Bono Internet (Home Office Bonus) | AG12: 138.25 | AH12: =(AG12/2)*4.33 -> 299.31125 | AK12: Bono Internet (Home Office Bonus) | AL12: 138.25 | AM12: =(AL12/2)*4.33 -> 299.31125 | AP12: Bono Internet (Home Office Bonus) | AQ12: 138.25 | AR12: =(AQ12/2)*4.33 -> 299.31125 | AV12: Bono Internet (Home Office Bonus) | AW12: 138.25 | AX12: =(AW12/2)*4.33 -> 299.31125 | BA12: Bono Internet (Home Office Bonus) | BB12: 138.25 | BC12: =(BB12/2)*4.33 -> 299.31125 | BE12: ROSARIO MORENO | BF12: =+AW46 -> 89068.477 | BG12: =+BF12*AX54 -> 0 | BH12: =+BF12+BG12 -> 89068.477 | BI12: =BH12/$BI$2 -> 4750.4708 | BK12: =+AW25 -> 53068.965 | BP12: Bono Internet (Home Office Bonus) | BQ12: 138.25 | BR12: =(BQ12/2)*4.33 -> 299.31125 | BU12: Bono Internet (Home Office Bonus) | BV12: 138.25 | BW12: =(BV12/2)*4.33 -> 299.31125
B13: Bono Mensual (Monthly Bonus) | C13: 12047.93 | D13: =(C13/2)*4.33 -> 26083.768 | G13: Bono Mensual (Monthly Bonus) | H13: 7004.61 | I13: =(H13/2)*4.33 -> 15164.981 | L13: Bono Mensual (Monthly Bonus) | M13: 7503.34 | N13: =(M13/2)*4.33 -> 16244.731 | Q13: Bono Mensual (Monthly Bonus) | R13: 46082.95 | S13: =(R13/2)*4.33 -> 99769.587 | V13: Bono Mensual (Monthly Bonus) | W13: 2565.416 | X13: =(W13/2)*4.33 -> 5554.1256 | AA13: Bono Mensual (Monthly Bonus) | AB13: 2937.788 | AC13: =(AB13/2)*4.33 -> 6360.311 | AF13: Bono Mensual (Monthly Bonus) | AG13: 2520 | AH13: =(AG13/2)*4.33 -> 5455.8 | AK13: Bono Mensual (Monthly Bonus) | AL13: 3394.076 | AM13: =(AL13/2)*4.33 -> 7348.1745 | AP13: Bono Mensual (Monthly Bonus) | AQ13: 2935.9638 | AR13: =(AQ13/2)*4.33 -> 6356.3616 | AV13: Bono Mensual (Monthly Bonus) | AW13: 32836.037 | AX13: =(AW13/2)*4.33 -> 71090.021 | BA13: Bono Mensual (Monthly Bonus) | BB13: 25429.082 | BC13: =(BB13/2)*4.33 -> 55053.962 | BG13: BASE EN MXN PARA FACTURAR---> | BH13: =SUM(BH4:BH12) -> 829048.88 | BI13: =BH13/$BI$2 -> 44217.355 | BK13: =SUM(BK4:BK12) -> 440752.3 | BP13: Bono Mensual (Monthly Bonus) | BQ13: 13806.596 | BR13: =(BQ13/2)*4.33 -> 29891.28 | BU13: Bono Mensual (Monthly Bonus) | BV13: 10541.178 | BW13: =(BV13/2)*4.33 -> 22821.649
B14: Bono PTU (PTU Bonus) | C14: 1520.58 | D14: =(C14/2)*4.33 -> 3292.0557 | G14: Bono PTU (PTU Bonus) | H14: 1520.58 | I14: =(H14/2)*4.33 -> 3292.0557 | L14: Bono PTU (PTU Bonus) | M14: 1520.58 | N14: =(M14/2)*4.33 -> 3292.0557 | Q14: Bono PTU (PTU Bonus | R14: 1520.58 | S14: =(R14/2)*4.33 -> 3292.0557 | V14: Bono PTU (PTU Bonus | W14: 1520.58 | X14: =(W14/2)*4.33 -> 3292.0557 | AA14: Bono PTU (PTU Bonus | AB14: 1520.58 | AC14: =(AB14/2)*4.33 -> 3292.0557 | AF14: Bono PTU (PTU Bonus | AG14: 1520.58 | AH14: =(AG14/2)*4.33 -> 3292.0557 | AK14: Bono PTU (PTU Bonus | AL14: 1520.58 | AM14: =(AL14/2)*4.33 -> 3292.0557 | AP14: Bono PTU (PTU Bonus | AQ14: 1520.58 | AR14: =(AQ14/2)*4.33 -> 3292.0557 | AV14: Bono PTU (PTU Bonus | AW14: 1520.58 | AX14: =(AW14/2)*4.33 -> 3292.0557 | BA14: Bono PTU (PTU Bonus | BB14: 1520.58 | BC14: =(BB14/2)*4.33 -> 3292.0557 | BI14: 0 | BP14: Bono PTU (PTU Bonus | BQ14: 1520.58 | BR14: =(BQ14/2)*4.33 -> 3292.0557 | BU14: Bono PTU (PTU Bonus | BV14: 1520.58 | BW14: =(BV14/2)*4.33 -> 3292.0557
B15: Prima Vacacional (Vacation Prime) | C15: 990.78 | D15: =(C15/2)*4.33 -> 2145.0387 | G15: Prima Vacacional (Vacation Prime) | H15: 576.04 | I15: =(H15/2)*4.33 -> 1247.1266 | L15: Prima Vacacional (Vacation Prime) | M15: 617.05 | N15: =(M15/2)*4.33 -> 1335.9132 | Q15: Prima Vacacional (Vacation Prime) | R15: 2027.65 | S15: =(R15/2)*4.33 -> 4389.8623 | V15: Prima Vacacional (Vacation Prime) | W15: 210.97 | X15: =(W15/2)*4.33 -> 456.75005 | AA15: Prima Vacacional (Vacation Prime) | AB15: 241.59441 | AC15: =(AB15/2)*4.33 -> 523.05189 | AF15: Prima Vacacional (Vacation Prime) | AG15: 207.24 | AH15: =(AG15/2)*4.33 -> 448.6746 | AK15: Prima Vacacional (Vacation Prime) | AL15: 558.23618 | AM15: =(AL15/2)*4.33 -> 1208.5813 | AP15: Prima Vacacional (Vacation Prime) | AQ15: 365.82484 | AR15: =(AQ15/2)*4.33 -> 792.01077 | AV15: Prima Vacacional (Vacation Prime) | AW15: 540.06641 | AX15: =(AW15/2)*4.33 -> 1169.2438 | BA15: Prima Vacacional (Vacation Prime) | BB15: 418.24147 | BC15: =(BB15/2)*4.33 -> 905.49279 | BP15: Prima Vacacional (Vacation Prime) | BQ15: 227.08217 | BR15: =(BQ15/2)*4.33 -> 491.63289 | BU15: Prima Vacacional (Vacation Prime) | BV15: 173.37463 | BW15: =(BV15/2)*4.33 -> 375.35608
B16: Total Percepcion(Total Gross Income) | C16: =SUM(C6:C15) -> 85892.7 | D16: =SUM(D6:D15) -> 185957.7 | G16: Total Percepcion(Total Gross Income) | H16: =SUM(H6:H15) -> 50639.24 | I16: =SUM(I6:I15) -> 109633.95 | L16: Total Percepcion(Total Gross Income) | M16: =SUM(M6:M15) -> 54125.41 | N16: =SUM(N6:N15) -> 117181.51 | Q16: Total Percepcion(Total Gross Income) | R16: =SUM(R6:R15) -> 195453.08 | S16: =SUM(S6:S15) -> 423155.92 | V16: Total Percepcion(Total Gross Income) | W16: =SUM(W6:W15) -> 34780.633 | X16: =SUM(X6:X15) -> 75300.071 | AA16: Total Percepcion(Total Gross Income) | AB16: =SUM(AB6:AB15) -> 39585.773 | AC16: =SUM(AC6:AC15) -> 85703.198 | AF16: Total Percepcion(Total Gross Income) | AG16: =SUM(AG6:AG15) -> 34194.58 | AH16: =SUM(AH6:AH15) -> 74031.266 | AK16: Total Percepcion(Total Gross Income) | AL16: =SUM(AL6:AL15) -> 45752.91 | AM16: =SUM(AM6:AM15) -> 99055.049 | AP16: Total Percepcion(Total Gross Income) | AQ16: =SUM(AQ6:AQ15) -> 57566.872 | AR16: =SUM(AR6:AR15) -> 124632.28 | AV16: Total Percepcion(Total Gross Income) | AW16: =SUM(AW6:AW15) -> 73850.583 | AX16: =SUM(AX6:AX15) -> 159886.51 | BA16: Total Percepcion(Total Gross Income) | BB16: =SUM(BB6:BB15) -> 57569.9 | BC16: =SUM(BC6:BC15) -> 124638.83 | BP16: Total Percepcion(Total Gross Income) | BQ16: =SUM(BQ6:BQ15) -> 32023.37 | BR16: =SUM(BR6:BR15) -> 69330.596 | BU16: Total Percepcion(Total Gross Income) | BV16: =SUM(BV6:BV15) -> 24845.895 | BW16: =SUM(BW6:BW15) -> 53791.364
A18: Deduccion (Deductions) | F18: Deduccion (Deductions) | K18: Deduccion (Deductions) | P18: Deduccion (Deductions) | U18: Deduccion (Deductions) | Z18: Deduccion (Deductions) | AE18: Deduccion (Deductions) | AJ18: Deduccion (Deductions) | AO18: Deduccion (Deductions) | AU18: Deduccion (Deductions) | AZ18: Deduccion (Deductions) | BO18: Deduccion (Deductions) | BT18: Deduccion (Deductions)
B19: IMSS Trabajador (Social Security) | C19: 1119.6653 | G19: IMSS Trabajador (Social Security) | H19: 999.43918 | L19: IMSS Trabajador (Social Security) | M19: 1072.0025 | Q19: IMSS Trabajador (Social Security) | R19: 1119.6653 | V19: IMSS Trabajador (Social Security) | W19: 727.3024 | AA19: IMSS Trabajador (Social Security) | AB19: 835.73152 | AF19: IMSS Trabajador (Social Security) | AG19: 714.07795 | AK19: IMSS Trabajador (Social Security) | AL19: 968.59571 | AP19: IMSS Trabajador (Social Security) | AQ19: 1119.6653 | AV19: IMSS Trabajador (Social Security) | AW19: 935.79881 | BA19: IMSS Trabajador (Social Security) | BB19: 720.26132 | BP19: IMSS Trabajador (Social Security) | BQ19: 382.05469 | BU19: IMSS Trabajador (Social Security) | BV19: 287.03319
B20: ISPT Trabajador (Federal Employee Tax) | C20: 23940.14 | D20: ? | G20: ISPT Trabajador (Federal Employee Tax) | H20: 12253.37 | L20: ISPT Trabajador (Federal Employee Tax) | M20: 13368.94 | Q20: ISPT Trabajador (Federal Employee Tax) | R20: 61190.66 | V20: ISPT Trabajador (Federal Employee Tax) | W20: 7468.5 | AA20: ISPT Trabajador (Federal Employee Tax) | AB20: 8910.04 | AF20: ISPT Trabajador (Federal Employee Tax) | AG20: 7292.68 | AK20: ISPT Trabajador (Federal Employee Tax) | AL20: 10760.18 | AP20: ISPT Trabajador (Federal Employee Tax) | AQ20: 14470.21 | AV20: ISPT Trabajador (Federal Employee Tax) | AW20: 19845.82 | BA20: ISPT Trabajador (Federal Employee Tax) | BB20: 14471.18 | BP20: ISPT Trabajador (Federal Employee Tax) | BQ20: 6641.32 | BU20: ISPT Trabajador (Federal Employee Tax) | BV20: 4558.86
B21: Total Deducciones (Ttoal deductions) | C21: =SUM(C19:C20) -> 25059.805 | D21: =C21/D33 -> 0.63179267 | G21: Total Deducciones (Ttoal deductions) | H21: =SUM(H19:H20) -> 13252.809 | I21: =H21/I33 -> 0.54859376 | L21: Total Deducciones (Ttoal deductions) | M21: =SUM(M19:M20) -> 14440.942 | N21: =M21/N33 -> 0.55335877 | Q21: Total Deducciones (Ttoal deductions) | R21: =SUM(R19:R20) -> 62310.325 | S21: =R21/S33 -> 0.73101297 | V21: Total Deducciones (Ttoal deductions) | W21: =SUM(W19:W20) -> 8195.8024 | X21: =W21/X33 -> 0.50726468 | AA21: Total Deducciones (Ttoal deductions) | AB21: =SUM(AB19:AB20) -> 9745.7715 | AC21: =AB21/AC33 -> 0.51810353 | AF21: Total Deducciones (Ttoal deductions) | AG21: =SUM(AG19:AG20) -> 8006.7579 | AH21: =AG21/AH33 -> 0.50569402 | AK21: Total Deducciones (Ttoal deductions) | AL21: =SUM(AL19:AL20) -> 11728.776 | AM21: =AL21/AM33 -> 0.52930996 | AP21: Total Deducciones (Ttoal deductions) | AQ21: =SUM(AQ19:AQ20) -> 15589.875 | AR21: =AQ21/AR33 -> 0.5553371 | AV21: Total Deducciones (Ttoal deductions) | AW21: =SUM(AW19:AW20) -> 20781.619 | AX21: =AW21/AX33 -> 0.64476959 | BA21: Total Deducciones (Ttoal deductions) | BB21: =SUM(BB19:BB20) -> 15191.441 | BC21: =BB21/BC33 -> 0.62933531 | BP21: Total Deducciones (Ttoal deductions) | BQ21: =SUM(BQ19:BQ20) -> 7023.3747 | BR21: =BQ21/BR33 -> 0.58310521 | BU21: Total Deducciones (Ttoal deductions) | BV21: =SUM(BV19:BV20) -> 4845.8932 | BW21: =BV21/BW33 -> 0.55291543
B25: Neto a Pagar (Total Week Net Pay) | C25: =C16-C21-C23 -> 60832.895 | G25: Neto a Pagar (Total Week Net Pay) | H25: =H16-H21-H23 -> 37386.431 | L25: Neto a Pagar (Total Week Net Pay) | M25: =M16-M21-M23 -> 39684.468 | Q25: Neto a Pagar (Total Week Net Pay) | R25: =R16-R21-R23 -> 133142.75 | V25: Neto a Pagar (Total Week Net Pay) | W25: =W16-W21-W23 -> 26584.831 | AA25: Neto a Pagar (Total Week Net Pay) | AB25: =AB16-AB21-AB23 -> 29840.001 | AF25: Neto a Pagar (Total Week Net Pay) | AG25: =AG16-AG21-AG23 -> 26187.822 | AK25: Neto a Pagar (Total Week Net Pay) | AL25: =AL16-AL21-AL23 -> 34024.134 | AP25: Neto a Pagar (Total Week Net Pay) | AQ25: =AQ16-AQ21-AQ23 -> 41976.997 | AV25: Neto a Pagar (Total Week Net Pay) | AW25: =AW16-AW21-AW23 -> 53068.965 | BA25: Neto a Pagar (Total Week Net Pay) | BB25: =BB16-BB21-BB23 -> 42378.459 | BP25: Neto a Pagar (Total Week Net Pay) | BQ25: =BQ16-BQ21-BQ23 -> 24999.996 | BU25: Neto a Pagar (Total Week Net Pay) | BV25: =BV16-BV21-BV23 -> 20000.002
A27: Impuesto Patronal (Employer Taxes) | F27: Impuesto Patronal (Employer Taxes) | K27: Impuesto Patronal (Employer Taxes) | P27: Impuesto Patronal (Employer Taxes) | U27: Impuesto Patronal (Employer Taxes) | Z27: Impuesto Patronal (Employer Taxes) | AE27: Impuesto Patronal (Employer Taxes) | AJ27: Impuesto Patronal (Employer Taxes) | AO27: Impuesto Patronal (Employer Taxes) | AU27: Impuesto Patronal (Employer Taxes) | AZ27: Impuesto Patronal (Employer Taxes) | BO27: Impuesto Patronal (Employer Taxes) | BT27: Impuesto Patronal (Employer Taxes)
B28: IMSS Empresa (Employer Social Security) | C28: 3606.5786 | G28: IMSS Empresa (Employer Social Security) | H28: 3255.6484 | L28: IMSS Empresa (Employer Social Security) | M28: 3467.4547 | Q28: IMSS Empresa (Employer Social Security) | R28: 3606.5786 | V28: IMSS Empresa (Employer Social Security) | W28: 2461.3032 | AA28: IMSS Empresa (Employer Social Security) | AB28: 2777.799 | AF28: IMSS Empresa (Employer Social Security) | AG28: 2422.7021 | AK28: IMSS Empresa (Employer Social Security) | AL28: 3165.6188 | AP28: IMSS Empresa (Employer Social Security) | AQ28: 3606.5786 | AV28: IMSS Empresa (Employer Social Security) | AW28: 3069.8873 | BA28: IMSS Empresa (Employer Social Security) | BB28: 2440.7508 | BP28: IMSS Empresa (Employer Social Security) | BQ28: 1453.5531 | BU28: IMSS Empresa (Employer Social Security) | BV28: 1176.193
B29: Infonavit (Employer housing) | C29: 3158.4384 | G29: Infonavit (Employer housing) | H29: 1836.3014 | L29: Infonavit (Employer housing) | M29: 1967.046 | Q29: Infonavit (Employer housing) | R29: 6463.7808 | V29: Infonavit (Employer housing) | W29: 1345.9648 | AA29: Infonavit (Employer housing) | AB29: 1541.3326 | AF29: Infonavit (Employer housing) | AG29: 1322.137 | AK29: Infonavit (Employer housing) | AL29: 1780.7275 | AP29: Infonavit (Employer housing) | AQ29: 2333.9023 | AV29: Infonavit (Employer housing) | AW29: 1721.634 | BA29: Infonavit (Employer housing) | BB29: 1333.2782 | BP29: Infonavit (Employer housing) | BQ29: 723.89688 | BU29: Infonavit (Employer housing) | BV29: 552.68697
B30: RCV (Employer retirement) | C30: 3905.8951 | G30: RCV (Employer retirement) | H30: 3493.747 | L30: RCV (Employer retirement) | M30: 3742.5018 | Q30: RCV (Employer retirement) | R30: 3905.8951 | V30: RCV (Employer retirement) | W30: 2560.8327 | AA30: RCV (Employer retirement) | AB30: 2932.5394 | AF30: RCV (Employer retirement) | AG30: 2515.4978 | AK30: RCV (Employer retirement) | AL30: 3388.01 | AP30: RCV (Employer retirement) | AQ30: 3905.8951 | AV30: RCV (Employer retirement) | AW30: 3275.5809 | BA30: RCV (Employer retirement) | BB30: 2536.6951 | BP30: RCV (Employer retirement) | BQ30: 1377.2862 | BU30: RCV (Employer retirement) | BV30: 1051.5422
B31: Impuesto Estatal (State Payroll Tax) | C31: 3933.8856 | G31: Impuesto Estatal (State Payroll Tax) | H31: 2319.2773 | L31: Impuesto Estatal (State Payroll Tax) | M31: 2478.9441 | Q31: Impuesto Estatal (State Payroll Tax) | R31: 8951.7504 | V31: Impuesto Estatal (State Payroll Tax) | W31: 1592.9531 | AA31: Impuesto Estatal (State Payroll Tax) | AB31: 1813.0288 | AF31: Impuesto Estatal (State Payroll Tax) | AG31: 1566.1118 | AK31: Impuesto Estatal (State Payroll Tax) | AL31: 2095.4833 | AP31: Impuesto Estatal (State Payroll Tax) | AQ31: 2636.5628 | AV31: Impuesto Estatal (State Payroll Tax) | AW31: 3382.3567 | BA31: Impuesto Estatal (State Payroll Tax) | BB31: 2636.7014 | BP31: Impuesto Estatal (State Payroll Tax) | BQ31: 1466.6704 | BU31: Impuesto Estatal (State Payroll Tax) | BV31: 1137.942
B32: Total Patronales (Total Employer Taxes) | C32: =SUM(C28:C31) -> 14604.798 | D32: =C32/D33 -> 0.36820733 | G32: Total Patronales (Total Employer Taxes) | H32: =SUM(H28:H31) -> 10904.974 | I32: =H32/I33 -> 0.45140624 | L32: Total Patronales (Total Employer Taxes) | M32: =SUM(M28:M31) -> 11655.947 | N32: =M32/N33 -> 0.44664123 | Q32: Total Patronales (Total Employer Taxes) | R32: =SUM(R28:R31) -> 22928.005 | S32: =R32/S33 -> 0.26898703 | V32: Total Patronales (Total Employer Taxes) | W32: =SUM(W28:W31) -> 7961.0538 | X32: =W32/X33 -> 0.49273532 | AA32: Total Patronales (Total Employer Taxes) | AB32: =SUM(AB28:AB31) -> 9064.6997 | AC32: =AB32/AC33 -> 0.48189647 | AF32: Total Patronales (Total Employer Taxes) | AG32: =SUM(AG28:AG31) -> 7826.4486 | AH32: =AG32/AH33 -> 0.49430598 | AK32: Total Patronales (Total Employer Taxes) | AL32: =SUM(AL28:AL31) -> 10429.84 | AM32: =AL32/AM33 -> 0.47069004 | AP32: Total Patronales (Total Employer Taxes) | AQ32: =SUM(AQ28:AQ31) -> 12482.939 | AR32: =AQ32/AR33 -> 0.4446629 | AV32: Total Patronales (Total Employer Taxes) | AW32: =SUM(AW28:AW31) -> 11449.459 | AX32: =AW32/AX33 -> 0.35523041 | BA32: Total Patronales (Total Employer Taxes) | BB32: =SUM(BB28:BB31) -> 8947.4255 | BC32: =BB32/BC33 -> 0.37066469 | BP32: Total Patronales (Total Employer Taxes) | BQ32: =SUM(BQ28:BQ31) -> 5021.4065 | BR32: =BQ32/BR33 -> 0.41689479 | BU32: Total Patronales (Total Employer Taxes) | BV32: =SUM(BV28:BV31) -> 3918.3643 | BW32: =BV32/BW33 -> 0.44708457
D33: =C32+C21 -> 39664.603 | I33: =H32+H21 -> 24157.783 | N33: =M32+M21 -> 26096.889 | S33: =R32+R21 -> 85238.33 | X33: =W32+W21 -> 16156.856 | AC33: =AB32+AB21 -> 18810.471 | AH33: =AG32+AG21 -> 15833.207 | AM33: =AL32+AL21 -> 22158.615 | AR33: =AQ32+AQ21 -> 28072.814 | AX33: =AW32+AW21 -> 32231.078 | BC33: =BB32+BB21 -> 24138.867 | BR33: =BQ32+BQ21 -> 12044.781 | BW33: =BV32+BV21 -> 8764.2575
B34: Operational Week Cost | C34: 1900 | G34: Operational Week Cost | H34: 1900 | L34: Operational Week Cost | M34: 1900 | Q34: Operational Week Cost | R34: 1900 | V34: Operational Week Cost | W34: 1900 | AA34: Operational Week Cost | AB34: 1900 | AF34: Operational Week Cost | AG34: 1900 | AK34: Operational Week Cost | AL34: 1900 | AP34: Operational Week Cost | AQ34: 1900 | AV34: Operational Week Cost | AW34: 1900 | BA34: Operational Week Cost | BB34: 1900 | BP34: Operational Week Cost | BQ34: 1900 | BU34: Operational Week Cost | BV34: 1900
A35: (1) | B35: PAYROLL BI-WEEK COST | C35: =C16+C32+C34 -> 102397.5 | F35: (1) | G35: PAYROLL BI-WEEK COST | H35: =H16+H32+H34 -> 63444.214 | K35: (1) | L35: PAYROLL BI-WEEK COST | M35: =M16+M32+M34 -> 67681.357 | P35: (1) | Q35: PAYROLL BI-WEEK COST | R35: =R16+R32+R34 -> 220281.08 | U35: (1) | V35: PAYROLL BI-WEEK COST | W35: =W16+W32+W34 -> 44641.687 | Z35: (1) | AA35: PAYROLL BI-WEEK COST | AB35: =AB16+AB32+AB34 -> 50550.472 | AE35: (1) | AF35: PAYROLL BI-WEEK COST | AG35: =AG16+AG32+AG34 -> 43921.029 | AJ35: (1) | AK35: PAYROLL BI-WEEK COST | AL35: =AL16+AL32+AL34 -> 58082.749 | AO35: (1) | AP35: PAYROLL BI-WEEK COST | AQ35: =AQ16+AQ32+AQ34 -> 71949.811 | AU35: (1) | AV35: PAYROLL BI-WEEK COST | AW35: =AW16+AW32+AW34 -> 87200.042 | AZ35: (1) | BA35: PAYROLL BI-WEEK COST | BB35: =BB16+BB32+BB34 -> 68417.325 | BO35: (1) | BP35: PAYROLL BI-WEEK COST | BQ35: =BQ16+BQ32+BQ34 -> 38944.777 | BT35: (1) | BU35: PAYROLL BI-WEEK COST | BV35: =BV16+BV32+BV34 -> 30664.26 | BZ35: Promedio de seguro
B37: Medical Annual | C37: =14696.6496852894+12000 -> 26696.65 | G37: Medical Annual | H37: =6423.97146896041+12000 -> 18423.971 | L37: Medical Annual | M37: =25771.3298876093+12000 -> 37771.33 | Q37: Medical Annual | R37: =29842.420288773+12000 -> 41842.42 | V37: Medical Annual | W37: =6423.97146896041+12000 -> 18423.971 | AA37: Medical Annual | AB37: =6423.97146896041+12000 -> 18423.971 | AF37: Medical Annual | AG37: =12000+39000 -> 51000 | AK37: Medical Annual | AL37: =12000+39000 -> 51000 | AP37: Medical Annual | AQ37: =12000+39000 -> 51000 | AR37: =+AQ37+AL37+AG37+AB37+W37+R37+M37+H37+C37 -> 314582.31 | AV37: Medical Annual | AW37: 41842.42 | AX37: Promedio de 11 personas | BA37: Medical Annual | BB37: 41842.42 | BC37: Promedio de 11 personas | BP37: Medical Annual | BQ37: 41842.42 | BR37: Promedio de 11 personas | BU37: Medical Annual | BV37: 41842.42 | BW37: Promedio de 11 personas | BZ37: Total de polizas | CA37: =+AQ37+AL37+AG37+AB37+W37+R37+M37+H37+C37+51000+51000 -> 416582.31
B38: Medical Monthly | C38: =+C37/12 -> 2224.7208 | G38: Medical Monthly | H38: =+H37/12 -> 1535.331 | L38: Medical Monthly | M38: =+M37/12 -> 3147.6108 | Q38: Medical Monthly | R38: =+R37/12 -> 3486.8684 | V38: Medical Monthly | W38: =+W37/12 -> 1535.331 | AA38: Medical Monthly | AB38: =+AB37/12 -> 1535.331 | AF38: Medical Monthly | AG38: =+AG37/12 -> 4250 | AK38: Medical Monthly | AL38: =+AL37/12 -> 4250 | AP38: Medical Monthly | AQ38: =+AQ37/12 -> 4250 | AR38: 9 | AV38: Medical Monthly | AW38: =+AW37/12 -> 3486.8683 | BA38: Medical Monthly | BB38: =+BB37/12 -> 3486.8683 | BP38: Medical Monthly | BQ38: =+BQ37/12 -> 3486.8683 | BU38: Medical Monthly | BV38: =+BV37/12 -> 3486.8683 | BZ38: Numero de personas | CA38: 11
A39: (2) | B39: Medical Bi-Weekly | C39: =+C38/2 -> 1112.3604 | F39: (2) | G39: Medical Bi-Weekly | H39: =+H38/2 -> 767.66548 | K39: (2) | L39: Medical Bi-Weekly | M39: =+M38/2 -> 1573.8054 | P39: (2) | Q39: Medical Bi-Weekly | R39: =+R38/2 -> 1743.4342 | U39: (2) | V39: Medical Bi-Weekly | W39: =+W38/2 -> 767.66548 | Z39: (2) | AA39: Medical Bi-Weekly | AB39: =+AB38/2 -> 767.66548 | AE39: (2) | AF39: Medical Bi-Weekly | AG39: =+AG38/2 -> 2125 | AJ39: (2) | AK39: Medical Bi-Weekly | AL39: =+AL38/2 -> 2125 | AO39: (2) | AP39: Medical Bi-Weekly | AQ39: =+AQ38/2 -> 2125 | AR39: =+AR37/9 -> 34953.59 | AU39: (2) | AV39: Medical Bi-Weekly | AW39: =+AW38/2 -> 1743.4342 | AZ39: (2) | BA39: Medical Bi-Weekly | BB39: =+BB38/2 -> 1743.4342 | BO39: (2) | BP39: Medical Bi-Weekly | BQ39: =+BQ38/2 -> 1743.4342 | BT39: (2) | BU39: Medical Bi-Weekly | BV39: =+BV38/2 -> 1743.4342 | BZ39: Promedio | CA39: =+CA37/CA38 -> 37871.119
B41: Life Insurance Annually | C41: 3000 | G41: Life Insurance Annually | H41: 3000 | L41: Life Insurance Annually | M41: 3000 | Q41: Life Insurance Annually | R41: 3000 | V41: Life Insurance Annually | W41: 3000 | AA41: Life Insurance Annually | AB41: 3000 | AF41: Life Insurance Annually | AG41: 3000 | AK41: Life Insurance Annually | AL41: 3000 | AP41: Life Insurance Annually | AQ41: 3000 | AR41: 51000 | AV41: Life Insurance Annually | AW41: 3000 | AX41: Revisar precio nuevo 2026/ $1008 | BA41: Life Insurance Annually | BB41: 3000 | BC41: Revisar precio nuevo 2026/ $1008 | BP41: Life Insurance Annually | BQ41: 3000 | BR41: Revisar precio nuevo 2026/ $1008 | BU41: Life Insurance Annually | BV41: 3000 | BW41: Revisar precio nuevo 2026/ $1008
B42: Life Insurance Montlhly | C42: =+C41/12 -> 250 | G42: Life Insurance Montlhly | H42: =+H41/12 -> 250 | L42: Life Insurance Montlhly | M42: =+M41/12 -> 250 | Q42: Life Insurance Montlhly | R42: =+R41/12 -> 250 | V42: Life Insurance Montlhly | W42: =+W41/12 -> 250 | AA42: Life Insurance Montlhly | AB42: =+AB41/12 -> 250 | AF42: Life Insurance Montlhly | AG42: =+AG41/12 -> 250 | AK42: Life Insurance Montlhly | AL42: =+AL41/12 -> 250 | AP42: Life Insurance Montlhly | AQ42: =+AQ41/12 -> 250 | AR42: =+AR41*11 -> 561000 | AV42: Life Insurance Montlhly | AW42: =+AW41/12 -> 250 | BA42: Life Insurance Montlhly | BB42: =+BB41/12 -> 250 | BP42: Life Insurance Montlhly | BQ42: =+BQ41/12 -> 250 | BU42: Life Insurance Montlhly | BV42: =+BV41/12 -> 250
A43: (3) | B43: Life Insurance Bi-Weekly | C43: =+C42/2 -> 125 | F43: (3) | G43: Life Insurance Bi-Weekly | H43: =+H42/2 -> 125 | K43: (3) | L43: Life Insurance Bi-Weekly | M43: =+M42/2 -> 125 | P43: (3) | Q43: Life Insurance Bi-Weekly | R43: =+R42/2 -> 125 | U43: (3) | V43: Life Insurance Bi-Weekly | W43: =+W42/2 -> 125 | Z43: (3) | AA43: Life Insurance Bi-Weekly | AB43: =+AB42/2 -> 125 | AE43: (3) | AF43: Life Insurance Bi-Weekly | AG43: =+AG42/2 -> 125 | AJ43: (3) | AK43: Life Insurance Bi-Weekly | AL43: =+AL42/2 -> 125 | AO43: (3) | AP43: Life Insurance Bi-Weekly | AQ43: =+AQ42/2 -> 125 | AU43: (3) | AV43: Life Insurance Bi-Weekly | AW43: =+AW42/2 -> 125 | AZ43: (3) | BA43: Life Insurance Bi-Weekly | BB43: =+BB42/2 -> 125 | BO43: (3) | BP43: Life Insurance Bi-Weekly | BQ43: =+BQ42/2 -> 125 | BT43: (3) | BU43: Life Insurance Bi-Weekly | BV43: =+BV42/2 -> 125 | BZ43: Monto Anual
BZ44: TC | CA44: 17
AU46: (1)+(2)+(3) | AV46: SUB-TOTAL 1 | AW46: =+AW39+AW35+AW43 -> 89068.477 | AZ46: (1)+(2)+(3) | BA46: SUB-TOTAL 1 | BB46: =+BB39+BB35+BB43 -> 70285.76 | BO46: (1)+(2)+(3) | BP46: SUB-TOTAL 1 | BQ46: =+BQ39+BQ35+BQ43 -> 40813.211 | BT46: (1)+(2)+(3) | BU46: SUB-TOTAL 1 | BV46: =+BV39+BV35+BV43 -> 32532.694
AV47: Service Fee | AW47: =+AW46*AX47 -> 9797.5324 | AX47: 0.11 | BA47: Service Fee | BB47: =+BB46*BC47 -> 7731.4335 | BC47: 0.11 | BP47: Service Fee | BQ47: =+BQ46*BR47 -> 4489.4532 | BR47: 0.11 | BU47: Service Fee | BV47: =+BV46*BW47 -> 3578.5963 | BW47: 0.11
AV48: GT BiWeekly invoice | AW48: =AW46+AW47 -> 98866.009 | BA48: GT BiWeekly invoice | BB48: =BB46+BB47 -> 78017.193 | BP48: GT BiWeekly invoice | BQ48: =BQ46+BQ47 -> 45302.664 | BU48: GT BiWeekly invoice | BV48: =BV46+BV47 -> 36111.29
A53: (1)+(2)+(3) | B53: SUB-TOTAL 1 | C53: =+C39+C35+C43 -> 103634.86 | F53: (1)+(2)+(3) | G53: SUB-TOTAL 1 | H53: =+H39+H35+H43 -> 64336.879 | K53: (1)+(2)+(3) | L53: SUB-TOTAL 1 | M53: =+M39+M35+M43 -> 69380.162 | P53: (1)+(2)+(3) | Q53: SUB-TOTAL 1 | R53: =+R39+R35+R43 -> 222149.52 | U53: (1)+(2)+(3) | V53: SUB-TOTAL 1 | W53: =+W39+W35+W43 -> 45534.352 | Z53: (1)+(2)+(3) | AA53: SUB-TOTAL 1 | AB53: =+AB39+AB35+AB43 -> 51443.138 | AE53: (1)+(2)+(3) | AF53: SUB-TOTAL 1 | AG53: =+AG39+AG35+AG43 -> 46171.029 | AJ53: (1)+(2)+(3) | AK53: SUB-TOTAL 1 | AL53: =+AL39+AL35+AL43 -> 60332.749 | AO53: (1)+(2)+(3) | AP53: SUB-TOTAL 1 | AQ53: =+AQ39+AQ35+AQ43 -> 74199.811 | BZ53: Anual dolares | CA53: 40000
B54: Service Fee | C54: =C53*D54 -> 11399.834 | D54: 0.11 | G54: Service Fee | H54: =H53*I54 -> 7077.0567 | I54: =D54 -> 0.11 | L54: Service Fee | M54: =M53*N54 -> 7631.8178 | N54: =I54 -> 0.11 | Q54: Service Fee | R54: =R53*S54 -> 24436.447 | S54: 0.11 | V54: Service Fee | W54: =W53*X54 -> 5919.4658 | X54: 0.13 | AA54: Service Fee | AB54: =AB53*AC54 -> 6687.6079 | AC54: 0.13 | AF54: Service Fee | AG54: =AG53*AH54 -> 6002.2337 | AH54: 0.13 | AK54: Service Fee | AL54: =AL53*AM54 -> 7843.2574 | AM54: 0.13 | AP54: Service Fee | AQ54: =AQ53*AR54 -> 9645.9755 | AR54: 0.13 | BZ54: Anual pesos mex | CA54: =+CA53*CA44 -> 680000
B55: GT BiWeekly invoice | C55: =C53+C54 -> 115034.69 | G55: GT BiWeekly invoice | H55: =H53+H54 -> 71413.936 | L55: GT BiWeekly invoice | M55: =M53+M54 -> 77011.98 | Q55: GT BiWeekly invoice | R55: =R53+R54 -> 246585.97 | V55: GT BiWeekly invoice | W55: =W53+W54 -> 51453.818 | AA55: GT BiWeekly invoice | AB55: =AB53+AB54 -> 58130.746 | AF55: GT BiWeekly invoice | AG55: =AG53+AG54 -> 52173.262 | AK55: GT BiWeekly invoice | AL55: =AL53+AL54 -> 68176.007 | AP55: GT BiWeekly invoice | AQ55: =AQ53+AQ54 -> 83845.787 | BZ55: 26 Quincenas | CA55: =+CA54/26 -> 26153.846
W58: Salary | AB58: Salary | AG58: Salary
W59: Service Fee | AB59: Service Fee | AG59: Service Fee
W60: GT | AB60: GT | AG60: GT
C67: =C55/D67 -> 6320.5875 | D67: 18.2 | H67: =H55/I67 -> 3923.8427 | I67: =D67 -> 18.2 | M67: =M55/N67 -> 4231.4275 | N67: =I67 -> 18.2 | R67: =R55/S67 -> 13548.679 | S67: =N67 -> 18.2
A69: Breakdown per category:
B79: CANTU | G79: MURRIETA | L79: SOTO | Q79: MORENO
B80: Salary Cost | C80: =C16+C34 -> 87792.7 | G80: Salary | H80: =H16+H34 -> 52539.24 | L80: Salary | M80: =M16+M34 -> 56025.41 | Q80: Salary | R80: =R16+R34 -> 197353.08
B81: Taxes and Benefits | C81: =C32+C39+C43 -> 15842.158 | G81: Taxes and Benefits | H81: =H32+H39+H43 -> 11797.639 | L81: Taxes and Benefits | M81: =M32+M39+M43 -> 13354.752 | Q81: Taxes and Benefits | R81: =R32+R39+R43 -> 24796.439
B82: Service Fee | C82: =C54 -> 11399.834 | G82: Service Fee | H82: =H54 -> 7077.0567 | L82: Service Fee | M82: =M54 -> 7631.8178 | Q82: Service Fee | R82: =R54 -> 24436.447
B83: GT | C83: =SUM(C80:C82) -> 115034.69 | G83: GT | H83: =SUM(H80:H82) -> 71413.936 | L83: GT | M83: =SUM(M80:M82) -> 77011.98 | Q83: GT | R83: =SUM(R80:R82) -> 246585.97
C84: =C55-C83 -> 0 | H84: =H55-H83 -> 0 | M84: =M55-M83 -> 0 | R84: =R55-R83 -> 0
Q86: Cantu/Murrieta/Soto/Moreno
Q87: Salary | R87: =C80+H80+M80+R80 -> 393710.43 | S87: =R87/$R$90 -> 0.77191074
Q88: Taxes and Benefits | R88: =C81+H81+M81+R81 -> 65790.989 | S88: =R88/$R$90 -> 0.12899016
Q89: Service Fee | R89: =C82+H82+M82+R82 -> 50545.156 | S89: =R89/$R$90 -> 0.099099099
Q90: GT | R90: =SUM(R87:R89) -> 510046.57 | S90: =R90/$R$90 -> 1
R91: =C83+H83+M83+R83 -> 510046.57
R93: =R91/25000 -> 20.401863

Sheet Simulacion Asimilado 
A1: CARLOS ALBERTO CANTU BARRON | F1: MASIEL MURRIETA VALDEZ | K1: JESUS ALBERTO SOTO MORA | P1: JESUS ALBERTO MORENO CORDOVA | U1: JORGE GUTIERREZ | Z1: DITHER ROSAS | AE1: JUAN CARLOS MENDOZA | AJ1: IVAN SALAZAR | AO1: Rosario Moreno | AU1: Generica | BC1: Santander Bank USA | BD1: 45903
AO2: Paquete incremento 10% | AP2: P | AV2: P | BD2: 18.7494
A3: SIMULACION SALARIO (Bi-Weekly Payroll FULL) | F3: SIMULACION SALARIO (Bi-Weekly Payroll FULL) | K3: SIMULACION SALARIO (Bi-Weekly Payroll FULL) | P3: SIMULACION SALARIO (Bi-Weekly Payroll FULL) | U3: SIMULACION SALARIO (Bi-Weekly Payroll FULL) | Z3: SIMULACION SALARIO (Bi-Weekly Payroll FULL) | AE3: SIMULACION SALARIO (Bi-Weekly Payroll FULL) | AJ3: SIMULACION SALARIO (Bi-Weekly Payroll FULL) | AO3: SIMULACION SALARIO (Bi-Weekly Payroll FULL) | AU3: SIMULACION SALARIO (Bi-Weekly Payroll FULL) | BA3: Bi-Weekly Gross Total (Fully Loaded) MXN | BB3: Bi-Weekly Service Fee MXN | BC3: Total Bi-Weekly Invoice MXN | BD3: Total Bi-Weekly Invoice USD* | BF3: NET PAY
AZ4: =+A1 -> CARLOS ALBERTO CANTU BARRON | BA4: =+C53 -> 103634.86 | BB4: =BA4*S54 -> 11399.834 | BC4: =+BB4+BA4 -> 115034.69 | BD4: =BC4/$BD$2 -> 6135.3799 | BF4: =+C25 -> 60832.895
A5: Percepcion (Gross Income): | C5: Weekly | D5: Monthly Reference | F5: Percepcion (Gross Income): | I5: Monthly Reference | K5: Percepcion (Gross Income): | N5: Monthly Reference | P5: Percepcion (Gross Income): | S5: Monthly Reference | U5: Percepcion (Gross Income): | W5: Actual | X5: Monthly Reference | Z5: Percepcion (Gross Income): | AB5: Actual | AC5: Monthly Reference | AE5: Percepcion (Gross Income): | AH5: Monthly Reference | AJ5: Percepcion (Gross Income): | AM5: Monthly Reference | AO5: Percepcion (Gross Income): | AR5: Monthly Reference | AU5: Percepcion (Gross Income): | AX5: Monthly Reference | AZ5: =+F1 -> MASIEL MURRIETA VALDEZ | BA5: =+H53 -> 64336.879 | BB5: =+BA5*S54 -> 7077.0567 | BC5: =+BB5+BA5 -> 71413.936 | BD5: =BC5/$BD$2 -> 3808.8652 | BF5: =+H25 -> 37386.431
B6: Sueldo Ordinario (Salary) | C6: 51600 | D6: =((C6+C7)/2)*4.33 -> 130333 | G6: Sueldo Ordinario (Salary) | H6: 30000 | I6: =((H6+H7)/2)*4.33 -> 75775 | L6: Sueldo Ordinario (Salary) | M6: 32136 | N6: =((M6+M7)/2)*4.33 -> 81170.18 | Q6: Sueldo Ordinario (Salary) | R6: 105600 | S6: =((R6+R7)/2)*4.33 -> 266728 | V6: Sueldo Ordinario (Salary) | W6: 21989.28 | X6: =((W6+W7)/2)*4.33 -> 55541.256 | AA6: Sueldo Ordinario (Salary) | AB6: 25181.04 | AC6: =((AB6+AB7)/2)*4.33 -> 63603.11 | AF6: Sueldo Ordinario (Salary) | AG6: 21600 | AH6: =((AG6+AG7)/2)*4.33 -> 54558 | AK6: Sueldo Ordinario (Salary) | AL6: 29092.08 | AM6: =((AL6+AL7)/2)*4.33 -> 73481.745 | AP6: Sueldo Ordinario (Salary) | AQ6: 38129.4 | AR6: =((AQ6+AQ7)/2)*4.33 -> 96308.509 | AV6: Sueldo Ordinario (Salary) | AW6: =+Simulacion!D6 -> 9029.3508 | AX6: =((AW6+AW7)/2)*4.33 -> 22806.635 | AZ6: =+K1 -> JESUS ALBERTO SOTO MORA | BA6: =+M53 -> 69380.162 | BB6: =+BA6*S54 -> 7631.8178 | BC6: =+BB6+BA6 -> 77011.98 | BD6: =BC6/$BD$2 -> 4107.437 | BF6: =+M25 -> 39684.468
B7: Septimo Dia (Seventh Day) | C7: 8600 | G7: Septimo Dia (Seventh Day) | H7: 5000 | L7: Septimo Dia (Seventh Day) | M7: 5356 | Q7: Septimo Dia (Seventh Day) | R7: 17600 | V7: Septimo Dia (Seventh Day) | W7: 3664.88 | AA7: Septimo Dia (Seventh Day) | AB7: 4196.84 | AF7: Septimo Dia (Seventh Day) | AG7: 3600 | AK7: Septimo Dia (Seventh Day) | AL7: 4848.68 | AP7: Septimo Dia (Seventh Day) | AQ7: 6354.9 | AV7: Septimo Dia (Seventh Day) | AW7: =+Simulacion!D7 -> 1504.8918 | AZ7: =+P1 -> JESUS ALBERTO MORENO CORDOVA | BA7: =+R53 -> 222149.52 | BB7: =+BA7*S54 -> 24436.447 | BC7: =+BB7+BA7 -> 246585.97 | BD7: =BC7/$BD$2 -> 13151.672 | BF7: =+R25 -> 133142.75
B8: Bono Fondo de Ahorro (5% Savings Fund) | C8: 3011.98 | D8: =(C8/2)*4.33 -> 6520.9367 | G8: Bono Fondo de Ahorro (5% Savings Fund) | H8: 1751.15 | I8: =(H8/2)*4.33 -> 3791.2398 | L8: Bono Fondo de Ahorro (5% Savings Fund) | M8: 1875.83 | N8: =(M8/2)*4.33 -> 4061.1719 | Q8: Bono Fondo de Ahorro (5% Savings Fund) | R8: 6164.06 | S8: =(R8/2)*4.33 -> 13345.19 | V8: Bono Fondo de Ahorro (5% Savings Fund) | W8: 1282.708 | X8: =(W8/2)*4.33 -> 2777.0628 | AA8: Bono Fondo de Ahorro (5% Savings Fund) | AB8: 1468.89 | AC8: =(AB8/2)*4.33 -> 3180.1469 | AF8: Bono Fondo de Ahorro (5% Savings Fund) | AG8: 1260 | AH8: =(AG8/2)*4.33 -> 2727.9 | AK8: Bono Fondo de Ahorro (5% Savings Fund) | AL8: 1697.038 | AM8: =(AL8/2)*4.33 -> 3674.0873 | AP8: Bono Fondo de Ahorro (5% Savings Fund) | AQ8: 2224.215 | AR8: =(AQ8/2)*4.33 -> 4815.4255 | AV8: Bono Fondo de Ahorro (5% Savings Fund) | AW8: =+Simulacion!D11 -> 527.05871 | AX8: =(AW8/2)*4.33 -> 1141.0821 | AZ8: =+U1 -> JORGE GUTIERREZ | BA8: =+W53 -> 45534.352 | BB8: =+BA8*X54 -> 5919.4658 | BC8: =+BB8+BA8 -> 51453.818 | BD8: =BC8/$BD$2 -> 2744.2915 | BF8: =+W25 -> 26584.831
B9: Bono Vale despensa (5% food Coupons) | C9: 3011.98 | D9: =(C9/2)*4.33 -> 6520.9367 | G9: Bono Vale despensa (5% food Coupons) | H9: 1751.15 | I9: =(H9/2)*4.33 -> 3791.2398 | L9: Bono Vale despensa (5% food Coupons) | M9: 1875.83 | N9: =(M9/2)*4.33 -> 4061.1719 | Q9: Bono Vale despensa (5% food Coupons) | R9: 6164.06 | S9: =(R9/2)*4.33 -> 13345.19 | V9: Bono Vale despensa (5% food Coupons) | W9: 1282.708 | X9: =(W9/2)*4.33 -> 2777.0628 | AA9: Bono Vale despensa (5% food Coupons) | AB9: 1468.89 | AC9: =(AB9/2)*4.33 -> 3180.1469 | AF9: Bono Vale despensa (5% food Coupons) | AG9: 1260 | AH9: =(AG9/2)*4.33 -> 2727.9 | AK9: Bono Vale despensa (5% food Coupons) | AL9: 1697.038 | AM9: =(AL9/2)*4.33 -> 3674.0873 | AP9: Bono Vale despensa (5% food Coupons) | AQ9: 2224.215 | AR9: =(AQ9/2)*4.33 -> 4815.4255 | AV9: Bono Vale despensa (5% food Coupons) | AW9: =+Simulacion!D12 -> 527.05871 | AX9: =(AW9/2)*4.33 -> 1141.0821 | AZ9: =+Z1 -> DITHER ROSAS | BA9: =+AB53 -> 51443.138 | BB9: =+BA9*AC54 -> 6687.6079 | BC9: =+BB9+BA9 -> 58130.746 | BD9: =BC9/$BD$2 -> 3100.4057 | BF9: =+AB25 -> 29840.001
B10: Aguinaldo | C10: 4953.92 | D10: =(C10/2)*4.33 -> 10725.237 | G10: Aguinaldo | H10: 2880.18 | I10: =(H10/2)*4.33 -> 6235.5897 | L10: Aguinaldo | M10: 3085.25 | N10: =(M10/2)*4.33 -> 6679.5662 | Q10: Aguinaldo | R10: 10138.25 | S10: =(R10/2)*4.33 -> 21949.311 | V10: Aguinaldo | W10: 2108.5611 | X10: =(W10/2)*4.33 -> 4565.0348 | AA10: Aguinaldo | AB10: 2414.6203 | AC10: =(AB10/2)*4.33 -> 5227.6529 | AF10: Aguinaldo | AG10: 2071.23 | AH10: =(AG10/2)*4.33 -> 4484.213 | AK10: Aguinaldo | AL10: 2789.6515 | AM10: =(AL10/2)*4.33 -> 6039.5955 | AP10: Aguinaldo | AQ10: 3656.2438 | AR10: =(AQ10/2)*4.33 -> 7915.7679 | AV10: Aguinaldo | AW10: =+Simulacion!D9 -> 866.87316 | AX10: =(AW10/2)*4.33 -> 1876.7804 | AZ10: =+AE1 -> JUAN CARLOS MENDOZA | BA10: =+AG53 -> 46171.029 | BB10: =+BA10*AH54 -> 6002.2337 | BC10: =+BB10+BA10 -> 52173.262 | BD10: =BC10/$BD$2 -> 2782.663 | BF10: =+AG25 -> 26187.822
B11: Bono Internet (Home Office Bonus) | C11: 138.25 | D11: =(C11/2)*4.33 -> 299.31125 | G11: Bono Navideño (Christmas Bonus) | H11: 17.28 | I11: =(H11/2)*4.33 -> 37.4112 | L11: Bono Internet (Home Office Bonus) | M11: 138.25 | N11: =(M11/2)*4.33 -> 299.31125 | Q11: Bono Navideño (Christmas Bonus) | R11: 17.28 | S11: =(R11/2)*4.33 -> 37.4112 | V11: Bono Navideño (Christmas Bonus) | W11: 17.28 | X11: =(W11/2)*4.33 -> 37.4112 | AA11: Bono Navideño (Christmas Bonus) | AB11: 17.28 | AC11: =(AB11/2)*4.33 -> 37.4112 | AF11: Bono Navideño (Christmas Bonus) | AG11: 17.28 | AH11: =(AG11/2)*4.33 -> 37.4112 | AK11: Bono Navideño (Christmas Bonus) | AL11: 17.28 | AM11: =(AL11/2)*4.33 -> 37.4112 | AP11: Bono Navideño (Christmas Bonus) | AQ11: 17.28 | AR11: =(AQ11/2)*4.33 -> 37.4112 | AV11: Bono Navideño (Christmas Bonus) | AW11: =+Simulacion!D14 -> 17.28 | AX11: =(AW11/2)*4.33 -> 37.4112 | AZ11: =+AJ1 -> IVAN SALAZAR | BA11: =+AL53 -> 60332.749 | BB11: =+BA11*AM54 -> 7843.2574 | BC11: =+BB11+BA11 -> 68176.007 | BD11: =BC11/$BD$2 -> 3636.17 | BF11: =+AL25 -> 34024.134
B12: Bono Navideño (Christmas Bonus) | C12: 17.28 | D12: =(C12/2)*4.33 -> 37.4112 | G12: Bono Internet (Home Office Bonus) | H12: 138.25 | I12: =(H12/2)*4.33 -> 299.31125 | L12: Bono Navideño (Christmas Bonus) | M12: 17.28 | N12: =(M12/2)*4.33 -> 37.4112 | Q12: Bono Internet (Home Office Bonus) | R12: 138.25 | S12: =(R12/2)*4.33 -> 299.31125 | V12: Bono Internet (Home Office Bonus) | W12: 138.25 | X12: =(W12/2)*4.33 -> 299.31125 | AA12: Bono Internet (Home Office Bonus) | AB12: 138.25 | AC12: =(AB12/2)*4.33 -> 299.31125 | AF12: Bono Internet (Home Office Bonus) | AG12: 138.25 | AH12: =(AG12/2)*4.33 -> 299.31125 | AK12: Bono Internet (Home Office Bonus) | AL12: 138.25 | AM12: =(AL12/2)*4.33 -> 299.31125 | AP12: Bono Internet (Home Office Bonus) | AQ12: 138.25 | AR12: =(AQ12/2)*4.33 -> 299.31125 | AV12: Bono Internet (Home Office Bonus) | AW12: =+Simulacion!D13 -> 138.25 | AX12: =(AW12/2)*4.33 -> 299.31125 | AZ12: ROSARIO MORENO | BA12: =+AW46 -> 28614.33 | BB12: =+BA12*AX54 -> 0 | BC12: =+BA12+BB12 -> 28614.33 | BD12: =BC12/$BD$2 -> 1526.1464 | BF12: =+AW25 -> 20328.231
B13: Bono Mensual (Monthly Bonus) | C13: 12047.93 | D13: =(C13/2)*4.33 -> 26083.768 | G13: Bono Mensual (Monthly Bonus) | H13: 7004.61 | I13: =(H13/2)*4.33 -> 15164.981 | L13: Bono Mensual (Monthly Bonus) | M13: 7503.34 | N13: =(M13/2)*4.33 -> 16244.731 | Q13: Bono Mensual (Monthly Bonus) | R13: 46082.95 | S13: =(R13/2)*4.33 -> 99769.587 | V13: Bono Mensual (Monthly Bonus) | W13: 2565.416 | X13: =(W13/2)*4.33 -> 5554.1256 | AA13: Bono Mensual (Monthly Bonus) | AB13: 2937.788 | AC13: =(AB13/2)*4.33 -> 6360.311 | AF13: Bono Mensual (Monthly Bonus) | AG13: 2520 | AH13: =(AG13/2)*4.33 -> 5455.8 | AK13: Bono Mensual (Monthly Bonus) | AL13: 3394.076 | AM13: =(AL13/2)*4.33 -> 7348.1745 | AP13: Bono Mensual (Monthly Bonus) | AQ13: 2935.9638 | AR13: =(AQ13/2)*4.33 -> 6356.3616 | AV13: Bono Mensual (Monthly Bonus) | AW13: =+Simulacion!D15 -> 10541.178 | AX13: =(AW13/2)*4.33 -> 22821.649 | BB13: BASE EN MXN PARA FACTURAR---> | BC13: =SUM(BC4:BC12) -> 768594.74 | BD13: =BC13/$BD$2 -> 40993.031 | BF13: =SUM(BF4:BF12) -> 408011.57
B14: Bono PTU (PTU Bonus) | C14: 1520.58 | D14: =(C14/2)*4.33 -> 3292.0557 | G14: Bono PTU (PTU Bonus) | H14: 1520.58 | I14: =(H14/2)*4.33 -> 3292.0557 | L14: Bono PTU (PTU Bonus) | M14: 1520.58 | N14: =(M14/2)*4.33 -> 3292.0557 | Q14: Bono PTU (PTU Bonus | R14: 1520.58 | S14: =(R14/2)*4.33 -> 3292.0557 | V14: Bono PTU (PTU Bonus | W14: 1520.58 | X14: =(W14/2)*4.33 -> 3292.0557 | AA14: Bono PTU (PTU Bonus | AB14: 1520.58 | AC14: =(AB14/2)*4.33 -> 3292.0557 | AF14: Bono PTU (PTU Bonus | AG14: 1520.58 | AH14: =(AG14/2)*4.33 -> 3292.0557 | AK14: Bono PTU (PTU Bonus | AL14: 1520.58 | AM14: =(AL14/2)*4.33 -> 3292.0557 | AP14: Bono PTU (PTU Bonus | AQ14: 1520.58 | AR14: =(AQ14/2)*4.33 -> 3292.0557 | AV14: Bono PTU (PTU Bonus | AW14: =+Simulacion!D10 -> 1520.58 | AX14: =(AW14/2)*4.33 -> 3292.0557 | BD14: 0
B15: Prima Vacacional (Vacation Prime) | C15: 990.78 | D15: =(C15/2)*4.33 -> 2145.0387 | G15: Prima Vacacional (Vacation Prime) | H15: 576.04 | I15: =(H15/2)*4.33 -> 1247.1266 | L15: Prima Vacacional (Vacation Prime) | M15: 617.05 | N15: =(M15/2)*4.33 -> 1335.9132 | Q15: Prima Vacacional (Vacation Prime) | R15: 2027.65 | S15: =(R15/2)*4.33 -> 4389.8623 | V15: Prima Vacacional (Vacation Prime) | W15: 210.97 | X15: =(W15/2)*4.33 -> 456.75005 | AA15: Prima Vacacional (Vacation Prime) | AB15: 241.59441 | AC15: =(AB15/2)*4.33 -> 523.05189 | AF15: Prima Vacacional (Vacation Prime) | AG15: 207.24 | AH15: =(AG15/2)*4.33 -> 448.6746 | AK15: Prima Vacacional (Vacation Prime) | AL15: 558.23618 | AM15: =(AL15/2)*4.33 -> 1208.5813 | AP15: Prima Vacacional (Vacation Prime) | AQ15: 365.82484 | AR15: =(AQ15/2)*4.33 -> 792.01077 | AV15: Prima Vacacional (Vacation Prime) | AW15: =+Simulacion!D8 -> 173.37463 | AX15: =(AW15/2)*4.33 -> 375.35608
B16: Total Percepcion(Total Gross Income) | C16: =SUM(C6:C15) -> 85892.7 | D16: =SUM(D6:D15) -> 185957.7 | G16: Total Percepcion(Total Gross Income) | H16: =SUM(H6:H15) -> 50639.24 | I16: =SUM(I6:I15) -> 109633.95 | L16: Total Percepcion(Total Gross Income) | M16: =SUM(M6:M15) -> 54125.41 | N16: =SUM(N6:N15) -> 117181.51 | Q16: Total Percepcion(Total Gross Income) | R16: =SUM(R6:R15) -> 195453.08 | S16: =SUM(S6:S15) -> 423155.92 | V16: Total Percepcion(Total Gross Income) | W16: =SUM(W6:W15) -> 34780.633 | X16: =SUM(X6:X15) -> 75300.071 | AA16: Total Percepcion(Total Gross Income) | AB16: =SUM(AB6:AB15) -> 39585.773 | AC16: =SUM(AC6:AC15) -> 85703.198 | AF16: Total Percepcion(Total Gross Income) | AG16: =SUM(AG6:AG15) -> 34194.58 | AH16: =SUM(AH6:AH15) -> 74031.266 | AK16: Total Percepcion(Total Gross Income) | AL16: =SUM(AL6:AL15) -> 45752.91 | AM16: =SUM(AM6:AM15) -> 99055.049 | AP16: Total Percepcion(Total Gross Income) | AQ16: =SUM(AQ6:AQ15) -> 57566.872 | AR16: =SUM(AR6:AR15) -> 124632.28 | AV16: Total Percepcion(Total Gross Income) | AW16: =SUM(AW6:AW15) -> 24845.895 | AX16: =SUM(AX6:AX15) -> 53791.364
A18: Deduccion (Deductions) | F18: Deduccion (Deductions) | K18: Deduccion (Deductions) | P18: Deduccion (Deductions) | U18: Deduccion (Deductions) | Z18: Deduccion (Deductions) | AE18: Deduccion (Deductions) | AJ18: Deduccion (Deductions) | AO18: Deduccion (Deductions) | AU18: Deduccion (Deductions)
B19: IMSS Trabajador (Social Security) | C19: 1119.6653 | G19: IMSS Trabajador (Social Security) | H19: 999.43918 | L19: IMSS Trabajador (Social Security) | M19: 1072.0025 | Q19: IMSS Trabajador (Social Security) | R19: 1119.6653 | V19: IMSS Trabajador (Social Security) | W19: 727.3024 | AA19: IMSS Trabajador (Social Security) | AB19: 835.73152 | AF19: IMSS Trabajador (Social Security) | AG19: 714.07795 | AK19: IMSS Trabajador (Social Security) | AL19: 968.59571 | AP19: IMSS Trabajador (Social Security) | AQ19: 1119.6653 | AV19: IMSS Trabajador (Social Security)
B20: ISPT Trabajador (Federal Employee Tax) | C20: 23940.14 | D20: ? | G20: ISPT Trabajador (Federal Employee Tax) | H20: 12253.37 | L20: ISPT Trabajador (Federal Employee Tax) | M20: 13368.94 | Q20: ISPT Trabajador (Federal Employee Tax) | R20: 61190.66 | V20: ISPT Trabajador (Federal Employee Tax) | W20: 7468.5 | AA20: ISPT Trabajador (Federal Employee Tax) | AB20: 8910.04 | AF20: ISPT Trabajador (Federal Employee Tax) | AG20: 7292.68 | AK20: ISPT Trabajador (Federal Employee Tax) | AL20: 10760.18 | AP20: ISPT Trabajador (Federal Employee Tax) | AQ20: 14470.21 | AV20: ISPT Trabajador (Federal Employee Tax) | AW20: =+'IMPUESTOS KOFILE'!E29 -> 4517.6646
B21: Total Deducciones (Ttoal deductions) | C21: =SUM(C19:C20) -> 25059.805 | D21: =C21/D33 -> 0.63179267 | G21: Total Deducciones (Ttoal deductions) | H21: =SUM(H19:H20) -> 13252.809 | I21: =H21/I33 -> 0.54859376 | L21: Total Deducciones (Ttoal deductions) | M21: =SUM(M19:M20) -> 14440.942 | N21: =M21/N33 -> 0.55335877 | Q21: Total Deducciones (Ttoal deductions) | R21: =SUM(R19:R20) -> 62310.325 | S21: =R21/S33 -> 0.73101297 | V21: Total Deducciones (Ttoal deductions) | W21: =SUM(W19:W20) -> 8195.8024 | X21: =W21/X33 -> 0.50726468 | AA21: Total Deducciones (Ttoal deductions) | AB21: =SUM(AB19:AB20) -> 9745.7715 | AC21: =AB21/AC33 -> 0.51810353 | AF21: Total Deducciones (Ttoal deductions) | AG21: =SUM(AG19:AG20) -> 8006.7579 | AH21: =AG21/AH33 -> 0.50569402 | AK21: Total Deducciones (Ttoal deductions) | AL21: =SUM(AL19:AL20) -> 11728.776 | AM21: =AL21/AM33 -> 0.52930996 | AP21: Total Deducciones (Ttoal deductions) | AQ21: =SUM(AQ19:AQ20) -> 15589.875 | AR21: =AQ21/AR33 -> 0.5553371 | AV21: Total Deducciones (Ttoal deductions) | AW21: =SUM(AW19:AW20) -> 4517.6646 | AX21: =AW21/AX33 -> 1
B25: Neto a Pagar (Total Week Net Pay) | C25: =C16-C21-C23 -> 60832.895 | G25: Neto a Pagar (Total Week Net Pay) | H25: =H16-H21-H23 -> 37386.431 | L25: Neto a Pagar (Total Week Net Pay) | M25: =M16-M21-M23 -> 39684.468 | Q25: Neto a Pagar (Total Week Net Pay) | R25: =R16-R21-R23 -> 133142.75 | V25: Neto a Pagar (Total Week Net Pay) | W25: =W16-W21-W23 -> 26584.831 | AA25: Neto a Pagar (Total Week Net Pay) | AB25: =AB16-AB21-AB23 -> 29840.001 | AF25: Neto a Pagar (Total Week Net Pay) | AG25: =AG16-AG21-AG23 -> 26187.822 | AK25: Neto a Pagar (Total Week Net Pay) | AL25: =AL16-AL21-AL23 -> 34024.134 | AP25: Neto a Pagar (Total Week Net Pay) | AQ25: =AQ16-AQ21-AQ23 -> 41976.997 | AV25: Neto a Pagar (Total Week Net Pay) | AW25: =AW16-AW21-AW23 -> 20328.231
A27: Impuesto Patronal (Employer Taxes) | F27: Impuesto Patronal (Employer Taxes) | K27: Impuesto Patronal (Employer Taxes) | P27: Impuesto Patronal (Employer Taxes) | U27: Impuesto Patronal (Employer Taxes) | Z27: Impuesto Patronal (Employer Taxes) | AE27: Impuesto Patronal (Employer Taxes) | AJ27: Impuesto Patronal (Employer Taxes) | AO27: Impuesto Patronal (Employer Taxes) | AU27: Impuesto Patronal (Employer Taxes)
B28: IMSS Empresa (Employer Social Security) | C28: 3606.5786 | G28: IMSS Empresa (Employer Social Security) | H28: 3255.6484 | L28: IMSS Empresa (Employer Social Security) | M28: 3467.4547 | Q28: IMSS Empresa (Employer Social Security) | R28: 3606.5786 | V28: IMSS Empresa (Employer Social Security) | W28: 2461.3032 | AA28: IMSS Empresa (Employer Social Security) | AB28: 2777.799 | AF28: IMSS Empresa (Employer Social Security) | AG28: 2422.7021 | AK28: IMSS Empresa (Employer Social Security) | AL28: 3165.6188 | AP28: IMSS Empresa (Employer Social Security) | AQ28: 3606.5786 | AV28: IMSS Empresa (Employer Social Security)
B29: Infonavit (Employer housing) | C29: 3158.4384 | G29: Infonavit (Employer housing) | H29: 1836.3014 | L29: Infonavit (Employer housing) | M29: 1967.046 | Q29: Infonavit (Employer housing) | R29: 6463.7808 | V29: Infonavit (Employer housing) | W29: 1345.9648 | AA29: Infonavit (Employer housing) | AB29: 1541.3326 | AF29: Infonavit (Employer housing) | AG29: 1322.137 | AK29: Infonavit (Employer housing) | AL29: 1780.7275 | AP29: Infonavit (Employer housing) | AQ29: 2333.9023 | AV29: Infonavit (Employer housing)
B30: RCV (Employer retirement) | C30: 3905.8951 | G30: RCV (Employer retirement) | H30: 3493.747 | L30: RCV (Employer retirement) | M30: 3742.5018 | Q30: RCV (Employer retirement) | R30: 3905.8951 | V30: RCV (Employer retirement) | W30: 2560.8327 | AA30: RCV (Employer retirement) | AB30: 2932.5394 | AF30: RCV (Employer retirement) | AG30: 2515.4978 | AK30: RCV (Employer retirement) | AL30: 3388.01 | AP30: RCV (Employer retirement) | AQ30: 3905.8951 | AV30: RCV (Employer retirement)
B31: Impuesto Estatal (State Payroll Tax) | C31: 3933.8856 | G31: Impuesto Estatal (State Payroll Tax) | H31: 2319.2773 | L31: Impuesto Estatal (State Payroll Tax) | M31: 2478.9441 | Q31: Impuesto Estatal (State Payroll Tax) | R31: 8951.7504 | V31: Impuesto Estatal (State Payroll Tax) | W31: 1592.9531 | AA31: Impuesto Estatal (State Payroll Tax) | AB31: 1813.0288 | AF31: Impuesto Estatal (State Payroll Tax) | AG31: 1566.1118 | AK31: Impuesto Estatal (State Payroll Tax) | AL31: 2095.4833 | AP31: Impuesto Estatal (State Payroll Tax) | AQ31: 2636.5628 | AV31: Impuesto Estatal (State Payroll Tax)
B32: Total Patronales (Total Employer Taxes) | C32: =SUM(C28:C31) -> 14604.798 | D32: =C32/D33 -> 0.36820733 | G32: Total Patronales (Total Employer Taxes) | H32: =SUM(H28:H31) -> 10904.974 | I32: =H32/I33 -> 0.45140624 | L32: Total Patronales (Total Employer Taxes) | M32: =SUM(M28:M31) -> 11655.947 | N32: =M32/N33 -> 0.44664123 | Q32: Total Patronales (Total Employer Taxes) | R32: =SUM(R28:R31) -> 22928.005 | S32: =R32/S33 -> 0.26898703 | V32: Total Patronales (Total Employer Taxes) | W32: =SUM(W28:W31) -> 7961.0538 | X32: =W32/X33 -> 0.49273532 | AA32: Total Patronales (Total Employer Taxes) | AB32: =SUM(AB28:AB31) -> 9064.6997 | AC32: =AB32/AC33 -> 0.48189647 | AF32: Total Patronales (Total Employer Taxes) | AG32: =SUM(AG28:AG31) -> 7826.4486 | AH32: =AG32/AH33 -> 0.49430598 | AK32: Total Patronales (Total Employer Taxes) | AL32: =SUM(AL28:AL31) -> 10429.84 | AM32: =AL32/AM33 -> 0.47069004 | AP32: Total Patronales (Total Employer Taxes) | AQ32: =SUM(AQ28:AQ31) -> 12482.939 | AR32: =AQ32/AR33 -> 0.4446629 | AV32: Total Patronales (Total Employer Taxes) | AW32: =SUM(AW28:AW31) -> 0 | AX32: =AW32/AX33 -> 0
D33: =C32+C21 -> 39664.603 | I33: =H32+H21 -> 24157.783 | N33: =M32+M21 -> 26096.889 | S33: =R32+R21 -> 85238.33 | X33: =W32+W21 -> 16156.856 | AC33: =AB32+AB21 -> 18810.471 | AH33: =AG32+AG21 -> 15833.207 | AM33: =AL32+AL21 -> 22158.615 | AR33: =AQ32+AQ21 -> 28072.814 | AX33: =AW32+AW21 -> 4517.6646
B34: Operational Week Cost | C34: 1900 | G34: Operational Week Cost | H34: 1900 | L34: Operational Week Cost | M34: 1900 | Q34: Operational Week Cost | R34: 1900 | V34: Operational Week Cost | W34: 1900 | AA34: Operational Week Cost | AB34: 1900 | AF34: Operational Week Cost | AG34: 1900 | AK34: Operational Week Cost | AL34: 1900 | AP34: Operational Week Cost | AQ34: 1900 | AV34: Operational Week Cost | AW34: 1900
A35: (1) | B35: PAYROLL BI-WEEK COST | C35: =C16+C32+C34 -> 102397.5 | F35: (1) | G35: PAYROLL BI-WEEK COST | H35: =H16+H32+H34 -> 63444.214 | K35: (1) | L35: PAYROLL BI-WEEK COST | M35: =M16+M32+M34 -> 67681.357 | P35: (1) | Q35: PAYROLL BI-WEEK COST | R35: =R16+R32+R34 -> 220281.08 | U35: (1) | V35: PAYROLL BI-WEEK COST | W35: =W16+W32+W34 -> 44641.687 | Z35: (1) | AA35: PAYROLL BI-WEEK COST | AB35: =AB16+AB32+AB34 -> 50550.472 | AE35: (1) | AF35: PAYROLL BI-WEEK COST | AG35: =AG16+AG32+AG34 -> 43921.029 | AJ35: (1) | AK35: PAYROLL BI-WEEK COST | AL35: =AL16+AL32+AL34 -> 58082.749 | AO35: (1) | AP35: PAYROLL BI-WEEK COST | AQ35: =AQ16+AQ32+AQ34 -> 71949.811 | AU35: (1) | AV35: PAYROLL BI-WEEK COST | AW35: =AW16+AW32+AW34 -> 26745.895 | BU35: Promedio de seguro
B37: Medical Annual | C37: =14696.6496852894+12000 -> 26696.65 | G37: Medical Annual | H37: =6423.97146896041+12000 -> 18423.971 | L37: Medical Annual | M37: =25771.3298876093+12000 -> 37771.33 | Q37: Medical Annual | R37: =29842.420288773+12000 -> 41842.42 | V37: Medical Annual | W37: =6423.97146896041+12000 -> 18423.971 | AA37: Medical Annual | AB37: =6423.97146896041+12000 -> 18423.971 | AF37: Medical Annual | AG37: =12000+39000 -> 51000 | AK37: Medical Annual | AL37: =12000+39000 -> 51000 | AP37: Medical Annual | AQ37: =12000+39000 -> 51000 | AR37: =+AQ37+AL37+AG37+AB37+W37+R37+M37+H37+C37 -> 314582.31 | AV37: Medical Annual | AW37: 41842.42 | AX37: Promedio de 9 personas | BU37: Total de polizas | BV37: =+AQ37+AL37+AG37+AB37+W37+R37+M37+H37+C37 -> 314582.31
B38: Medical Monthly | C38: =+C37/12 -> 2224.7208 | G38: Medical Monthly | H38: =+H37/12 -> 1535.331 | L38: Medical Monthly | M38: =+M37/12 -> 3147.6108 | Q38: Medical Monthly | R38: =+R37/12 -> 3486.8684 | V38: Medical Monthly | W38: =+W37/12 -> 1535.331 | AA38: Medical Monthly | AB38: =+AB37/12 -> 1535.331 | AF38: Medical Monthly | AG38: =+AG37/12 -> 4250 | AK38: Medical Monthly | AL38: =+AL37/12 -> 4250 | AP38: Medical Monthly | AQ38: =+AQ37/12 -> 4250 | AR38: 9 | AV38: Medical Monthly | AW38: =+AW37/12 -> 3486.8683 | BU38: Numero de personas | BV38: 9
A39: (2) | B39: Medical Bi-Weekly | C39: =+C38/2 -> 1112.3604 | F39: (2) | G39: Medical Bi-Weekly | H39: =+H38/2 -> 767.66548 | K39: (2) | L39: Medical Bi-Weekly | M39: =+M38/2 -> 1573.8054 | P39: (2) | Q39: Medical Bi-Weekly | R39: =+R38/2 -> 1743.4342 | U39: (2) | V39: Medical Bi-Weekly | W39: =+W38/2 -> 767.66548 | Z39: (2) | AA39: Medical Bi-Weekly | AB39: =+AB38/2 -> 767.66548 | AE39: (2) | AF39: Medical Bi-Weekly | AG39: =+AG38/2 -> 2125 | AJ39: (2) | AK39: Medical Bi-Weekly | AL39: =+AL38/2 -> 2125 | AO39: (2) | AP39: Medical Bi-Weekly | AQ39: =+AQ38/2 -> 2125 | AR39: =+AR37/9 -> 34953.59 | AU39: (2) | AV39: Medical Bi-Weekly | AW39: =+AW38/2 -> 1743.4342 | BU39: Promedio | BV39: =+BV37/BV38 -> 34953.59
B41: Life Insurance Annually | C41: 3000 | G41: Life Insurance Annually | H41: 3000 | L41: Life Insurance Annually | M41: 3000 | Q41: Life Insurance Annually | R41: 3000 | V41: Life Insurance Annually | W41: 3000 | AA41: Life Insurance Annually | AB41: 3000 | AF41: Life Insurance Annually | AG41: 3000 | AK41: Life Insurance Annually | AL41: 3000 | AP41: Life Insurance Annually | AQ41: 3000 | AV41: Life Insurance Annually | AW41: 3000 | AX41: Revisar precio nuevo 2026/ $1008
B42: Life Insurance Montlhly | C42: =+C41/12 -> 250 | G42: Life Insurance Montlhly | H42: =+H41/12 -> 250 | L42: Life Insurance Montlhly | M42: =+M41/12 -> 250 | Q42: Life Insurance Montlhly | R42: =+R41/12 -> 250 | V42: Life Insurance Montlhly | W42: =+W41/12 -> 250 | AA42: Life Insurance Montlhly | AB42: =+AB41/12 -> 250 | AF42: Life Insurance Montlhly | AG42: =+AG41/12 -> 250 | AK42: Life Insurance Montlhly | AL42: =+AL41/12 -> 250 | AP42: Life Insurance Montlhly | AQ42: =+AQ41/12 -> 250 | AV42: Life Insurance Montlhly | AW42: =+AW41/12 -> 250
A43: (3) | B43: Life Insurance Bi-Weekly | C43: =+C42/2 -> 125 | F43: (3) | G43: Life Insurance Bi-Weekly | H43: =+H42/2 -> 125 | K43: (3) | L43: Life Insurance Bi-Weekly | M43: =+M42/2 -> 125 | P43: (3) | Q43: Life Insurance Bi-Weekly | R43: =+R42/2 -> 125 | U43: (3) | V43: Life Insurance Bi-Weekly | W43: =+W42/2 -> 125 | Z43: (3) | AA43: Life Insurance Bi-Weekly | AB43: =+AB42/2 -> 125 | AE43: (3) | AF43: Life Insurance Bi-Weekly | AG43: =+AG42/2 -> 125 | AJ43: (3) | AK43: Life Insurance Bi-Weekly | AL43: =+AL42/2 -> 125 | AO43: (3) | AP43: Life Insurance Bi-Weekly | AQ43: =+AQ42/2 -> 125 | AU43: (3) | AV43: Life Insurance Bi-Weekly | AW43: =+AW42/2 -> 125 | BU43: Monto Anual
BU44: TC | BV44: 17
AU46: (1)+(2)+(3) | AV46: SUB-TOTAL 1 | AW46: =+AW39+AW35+AW43 -> 28614.33
AV47: Service Fee | AW47: =+AW46*AX47 -> 3147.5763 | AX47: 0.11
AV48: GT BiWeekly invoice | AW48: =AW46+AW47 -> 31761.906
A53: (1)+(2)+(3) | B53: SUB-TOTAL 1 | C53: =+C39+C35+C43 -> 103634.86 | F53: (1)+(2)+(3) | G53: SUB-TOTAL 1 | H53: =+H39+H35+H43 -> 64336.879 | K53: (1)+(2)+(3) | L53: SUB-TOTAL 1 | M53: =+M39+M35+M43 -> 69380.162 | P53: (1)+(2)+(3) | Q53: SUB-TOTAL 1 | R53: =+R39+R35+R43 -> 222149.52 | U53: (1)+(2)+(3) | V53: SUB-TOTAL 1 | W53: =+W39+W35+W43 -> 45534.352 | Z53: (1)+(2)+(3) | AA53: SUB-TOTAL 1 | AB53: =+AB39+AB35+AB43 -> 51443.138 | AE53: (1)+(2)+(3) | AF53: SUB-TOTAL 1 | AG53: =+AG39+AG35+AG43 -> 46171.029 | AJ53: (1)+(2)+(3) | AK53: SUB-TOTAL 1 | AL53: =+AL39+AL35+AL43 -> 60332.749 | AO53: (1)+(2)+(3) | AP53: SUB-TOTAL 1 | AQ53: =+AQ39+AQ35+AQ43 -> 74199.811 | BU53: Anual dolares | BV53: 40000
B54: Service Fee | C54: =C53*D54 -> 11399.834 | D54: 0.11 | G54: Service Fee | H54: =H53*I54 -> 7077.0567 | I54: =D54 -> 0.11 | L54: Service Fee | M54: =M53*N54 -> 7631.8178 | N54: =I54 -> 0.11 | Q54: Service Fee | R54: =R53*S54 -> 24436.447 | S54: 0.11 | V54: Service Fee | W54: =W53*X54 -> 5919.4658 | X54: 0.13 | AA54: Service Fee | AB54: =AB53*AC54 -> 6687.6079 | AC54: 0.13 | AF54: Service Fee | AG54: =AG53*AH54 -> 6002.2337 | AH54: 0.13 | AK54: Service Fee | AL54: =AL53*AM54 -> 7843.2574 | AM54: 0.13 | AP54: Service Fee | AQ54: =AQ53*AR54 -> 9645.9755 | AR54: 0.13 | BU54: Anual pesos mex | BV54: =+BV53*BV44 -> 680000
B55: GT BiWeekly invoice | C55: =C53+C54 -> 115034.69 | G55: GT BiWeekly invoice | H55: =H53+H54 -> 71413.936 | L55: GT BiWeekly invoice | M55: =M53+M54 -> 77011.98 | Q55: GT BiWeekly invoice | R55: =R53+R54 -> 246585.97 | V55: GT BiWeekly invoice | W55: =W53+W54 -> 51453.818 | AA55: GT BiWeekly invoice | AB55: =AB53+AB54 -> 58130.746 | AF55: GT BiWeekly invoice | AG55: =AG53+AG54 -> 52173.262 | AK55: GT BiWeekly invoice | AL55: =AL53+AL54 -> 68176.007 | AP55: GT BiWeekly invoice | AQ55: =AQ53+AQ54 -> 83845.787 | BU55: 26 Quincenas | BV55: =+BV54/26 -> 26153.846
W58: Salary | AB58: Salary | AG58: Salary
W59: Service Fee | AB59: Service Fee | AG59: Service Fee
W60: GT | AB60: GT | AG60: GT
C67: =C55/D67 -> 6320.5875 | D67: 18.2 | H67: =H55/I67 -> 3923.8427 | I67: =D67 -> 18.2 | M67: =M55/N67 -> 4231.4275 | N67: =I67 -> 18.2 | R67: =R55/S67 -> 13548.679 | S67: =N67 -> 18.2
A69: Breakdown per category:
B79: CANTU | G79: MURRIETA | L79: SOTO | Q79: MORENO
B80: Salary Cost | C80: =C16+C34 -> 87792.7 | G80: Salary | H80: =H16+H34 -> 52539.24 | L80: Salary | M80: =M16+M34 -> 56025.41 | Q80: Salary | R80: =R16+R34 -> 197353.08
B81: Taxes and Benefits | C81: =C32+C39+C43 -> 15842.158 | G81: Taxes and Benefits | H81: =H32+H39+H43 -> 11797.639 | L81: Taxes and Benefits | M81: =M32+M39+M43 -> 13354.752 | Q81: Taxes and Benefits | R81: =R32+R39+R43 -> 24796.439
B82: Service Fee | C82: =C54 -> 11399.834 | G82: Service Fee | H82: =H54 -> 7077.0567 | L82: Service Fee | M82: =M54 -> 7631.8178 | Q82: Service Fee | R82: =R54 -> 24436.447
B83: GT | C83: =SUM(C80:C82) -> 115034.69 | G83: GT | H83: =SUM(H80:H82) -> 71413.936 | L83: GT | M83: =SUM(M80:M82) -> 77011.98 | Q83: GT | R83: =SUM(R80:R82) -> 246585.97
C84: =C55-C83 -> 0 | H84: =H55-H83 -> 0 | M84: =M55-M83 -> 0 | R84: =R55-R83 -> 0
Q86: Cantu/Murrieta/Soto/Moreno
Q87: Salary | R87: =C80+H80+M80+R80 -> 393710.43 | S87: =R87/$R$90 -> 0.77191074
Q88: Taxes and Benefits | R88: =C81+H81+M81+R81 -> 65790.989 | S88: =R88/$R$90 -> 0.12899016
Q89: Service Fee | R89: =C82+H82+M82+R82 -> 50545.156 | S89: =R89/$R$90 -> 0.099099099
Q90: GT | R90: =SUM(R87:R89) -> 510046.57 | S90: =R90/$R$90 -> 1
R91: =C83+H83+M83+R83 -> 510046.57
R93: =R91/25000 -> 20.401863

Sheet IMPUESTOS KOFILE
B1: KOFILE ASIMILADO SEMANAL | G1: TARIFA SEMANAL ISR 2026
B2: Percepcion: | G2: Límite inferior | H2: Límite superior | I2: Cuota fija | J2: Por ciento para aplicarse sobre el excedente del límite inferior
C3: Ingresos Gravados | D3: 16837.56 | G3: $ | H3: $ | I3: $ | J3: %
C4: Límite Inferior | D4: =IF(D3>$G$14,$G$14,VLOOKUP(D3,$G$4:$J$14,1)) -> 12834.09 | G4: 0.01 | H4: 194.46 | I4: 0 | J4: 0.0192
C5: Excedente Lim. Inferior | D5: =+D3-D4 -> 4003.47 | G5: 194.47 | H5: 1650.67 | I5: 3.71 | J5: 0.064
C6: % sobre excedente | D6: =VLOOKUP(D3,$G$4:$J$14,4) -> 0.3 | G6: 1650.68 | H6: 2900.87 | I6: 96.95 | J6: 0.1088
C7: ISR S/Excedente | D7: =D5*D6 -> 1201.041 | G7: 2900.88 | H7: 3372.11 | I7: 232.96 | J7: 0.16
C8: Cuota Fija | D8: =VLOOKUP(D3,$G$4:$J$14,3) -> 2407.86 | G8: 3372.12 | H8: 4037.32 | I8: 308.35 | J8: 0.1792
C9: ISR a Retener del mes | D9: =+D7+D8 -> 3608.901 | G9: 4037.33 | H9: 8142.75 | I9: 427.56 | J9: 0.2136
C10: SUBSIDIO | D10: 0 | G10: 8142.76 | H10: 12834.08 | I10: 1304.45 | J10: 0.2352
B11: Deduccion: | C11: ISR | D11: =+D9-D10 -> 3608.901 | G11: 12834.09 | H11: 24502.45 | I11: 2407.86 | J11: 0.3
G12: 24502.46 | H12: 32669.91 | I12: 5908.35 | J12: 0.32
C13: Neto semanal | D13: =+D3-D11 -> 13228.659 | G13: 32669.92 | H13: 98009.66 | I13: 8521.94 | J13: 0.34
C14: Neto esperado | D14: 13228.66 | G14: 98009.67 | H14: En adelante | I14: 30737.49 | J14: 0.35
C15: Diferencia | D15: =+D13-D14 -> -0.001
B19: KOFILE ASIMILADO CATORCENAL | E19: Considerar esta columna | G19: TARIFA MENSUAL ISR 2026
B20: Percepcion: | G20: Límite inferior | H20: Límite superior | I20: Cuota fija | J20: Por ciento para aplicarse sobre el excedente del límite inferior
C21: Ingresos Gravados | D21: =+'Simulacion Asimilado '!AW16*2 -> 49691.791 | E21: =+D21/2 -> 24845.895 | G21: $ | H21: $ | I21: $ | J21: %
C22: Límite Inferior | D22: =IF(D21>$G$32,$G$32,VLOOKUP(D21,$G$22:$J$32,1)) -> 35362.84 | G22: 0.01 | H22: 844.59 | I22: 0 | J22: 0.0192
C23: Excedente Lim. Inferior | D23: =+D21-D22 -> 14328.951 | G23: 844.6 | H23: 7168.51 | I23: 16.22 | J23: 0.064
C24: % sobre excedente | D24: =VLOOKUP(D21,$G$22:$J$32,4) -> 0.2352 | G24: 7168.52 | H24: 12598.02 | I24: 420.95 | J24: 0.1088
C25: ISR S/Excedente | D25: =D23*D24 -> 3370.1692 | G25: 12598.03 | H25: 14644.64 | I25: 1011.68 | J25: 0.16
C26: Cuota Fija | D26: =VLOOKUP(D21,$G$22:$J$32,3) -> 5665.16 | G26: 14644.65 | H26: 17533.64 | I26: 1339.14 | J26: 0.1792
C27: ISR a Retener del mes | D27: =+D25+D26 -> 9035.3292 | G27: 17533.65 | H27: 35362.83 | I27: 1856.84 | J27: 0.2136
C28: SUBSIDIO | D28: 0 | G28: 35362.84 | H28: 55736.68 | I28: 5665.16 | J28: 0.2352
B29: Deduccion: | C29: ISR | D29: =+D27-D28 -> 9035.3292 | E29: =+D29/2 -> 4517.6646 | G29: 55736.69 | H29: 106410.5 | I29: 10457.09 | J29: 0.3
G30: 106410.51 | H30: 141880.66 | I30: 25659.23 | J30: 0.32
C31: Neto semanal | D31: =+D21-D29 -> 40656.462 | E31: =+E21-E29 -> 20328.231 | G31: 141880.67 | H31: 425641.99 | I31: 37009.69 | J31: 0.34
C32: Neto esperado | D32: 0 | E32: 0 | G32: 425642 | H32: En adelante | I32: 133488.54 | J32: 0.35
C33: Diferencia | D33: =+D32-E32 -> 0
B38: KOFILE ASIMILADO CATORCENAL PROPORCIONAL | G38: TARIFA MENSUAL ISR 2026 | L38: TARIFA MENSUAL ISR 2026 PROPORCIONES
B39: Percepcion: | G39: Límite inferior | H39: Límite superior | I39: Cuota fija | J39: Por ciento para aplicarse sobre el excedente del límite inferior | L39: Límite inferior | M39: Límite superior | N39: Cuota fija | O39: Por ciento para aplicarse sobre el excedente del límite inferior
C40: Ingresos Gravados | D40: 15715.95 | G40: $ | H40: $ | I40: $ | J40: % | L40: $ | M40: $ | N40: $ | O40: %
C41: Límite Inferior | D41: =IF(D40>$L$51,$L$51,VLOOKUP(D40,$L$41:$O$51,1)) -> 8074.7072 | G41: 0.01 | H41: 844.59 | I41: 0 | J41: 0.0192 | L41: 0.0046052632 | M41: 388.95592 | N41: 0 | O41: 0.0192
C42: Excedente Lim. Inferior | D42: =+D40-D41 -> 7641.2428 | G42: 844.6 | H42: 7168.51 | I42: 16.22 | J42: 0.064 | L42: 388.96053 | M42: 3301.2875 | N42: =+(I42/30.4)*14 -> 7.4697368 | O42: 0.064
C43: % sobre excedente | D43: =VLOOKUP(D40,$L$41:$O$51,4) -> 0.2136 | G43: 7168.52 | H43: 12598.02 | I43: 420.95 | J43: 0.1088 | L43: 3301.2921 | M43: 5801.7197 | N43: =+(I43/30.4)*14 -> 193.85855 | O43: 0.1088
C44: ISR S/Excedente | D44: =D42*D43 -> 1632.1695 | G44: 12598.03 | H44: 14644.64 | I44: 1011.68 | J44: 0.16 | L44: 5801.7243 | M44: 6744.2421 | N44: =+(I44/30.4)*14 -> 465.90526 | O44: 0.16
C45: Cuota Fija | D45: =VLOOKUP(D40,$L$41:$O$51,3) -> 855.12368 | G45: 14644.65 | H45: 17533.64 | I45: 1339.14 | J45: 0.1792 | L45: 6744.2467 | M45: 8074.7026 | N45: =+(I45/30.4)*14 -> 616.70921 | O45: 0.1792
C46: ISR a Retener del mes | D46: =+D44+D45 -> 2487.2931 | G46: 17533.65 | H46: 35362.83 | I46: 1856.84 | J46: 0.2136 | L46: 8074.7072 | M46: 16285.514 | N46: =+(I46/30.4)*14 -> 855.12368 | O46: 0.2136
C47: SUBSIDIO | D47: 0 | G47: 35362.84 | H47: 55736.68 | I47: 5665.16 | J47: 0.2352 | L47: 16285.518 | M47: 25668.208 | N47: =+(I47/30.4)*14 -> 2608.9553 | O47: 0.2352
B48: Deduccion: | C48: ISR | D48: =+D46-D47 -> 2487.2931 | G48: 55736.69 | H48: 106410.5 | I48: 10457.09 | J48: 0.3 | L48: 25668.213 | M48: 49004.836 | N48: =+(I48/30.4)*14 -> 4815.7651 | O48: 0.3
G49: 106410.51 | H49: 141880.66 | I49: 25659.23 | J49: 0.32 | L49: 49004.84 | M49: 65339.778 | N49: =+(I49/30.4)*14 -> 11816.751 | O49: 0.32
C50: Neto semanal | D50: =+D40-D48 -> 13228.657 | G50: 141880.67 | H50: 425641.99 | I50: 37009.69 | J50: 0.34 | L50: 65339.782 | M50: 196019.34 | N50: =+(I50/30.4)*14 -> 17043.936 | O50: 0.34
C51: Neto esperado | D51: 13228.66 | G51: 425642 | H51: En adelante | I51: 133488.54 | J51: 0.35 | L51: 196019.34 | M51: 0 | N51: =+(I51/30.4)*14 -> 61474.986 | O51: 0.35
C52: Diferencia | D52: =+D50-D51 -> -0.0031384211
B55: Perc Catorcenal | C55: Catorcenas al año | D55: Percepcion anualizada | G55: TARIFA ANUAL ISR 2026
B56: 15716.56 | C56: =TRUNC((365/14),4) -> 26.0714 | D56: =+B56*C56 -> 409752.72 | G56: Límite inferior | H56: Límite superior | I56: Cuota fija | J56: Por ciento para aplicarse sobre el excedente del límite inferior
G57: $ | H57: $ | I57: $ | J57: %
B58: Percepcion: | G58: 0.01 | H58: 10135.11 | I58: 0 | J58: 0.0192
C59: Ingresos Gravados | D59: =+D56 -> 409752.72 | G59: 10135.12 | H59: 86022.11 | I59: 194.59 | J59: 0.064
C60: Límite Inferior | D60: =IF(D59>$G$68,$G$68,VLOOKUP(D59,$G$58:$J$68,1)) -> 210403.7 | G60: 86022.12 | H60: 151176.19 | I60: 5051.37 | J60: 0.1088
C61: Excedente Lim. Inferior | D61: =+D59-D60 -> 199349.02 | G61: 151176.2 | H61: 175735.66 | I61: 12140.13 | J61: 0.16
C62: % sobre excedente | D62: =VLOOKUP(D59,$G$58:$J$68,4) -> 0.2136 | G62: 175735.67 | H62: 210403.69 | I62: 16069.64 | J62: 0.1792
C63: ISR S/Excedente | D63: =D61*D62 -> 42580.951 | G63: 210403.7 | H63: 424353.97 | I63: 22282.14 | J63: 0.2136
C64: Cuota Fija | D64: =VLOOKUP(D59,$G$58:$J$68,3) -> 22282.14 | G64: 424353.98 | H64: 668840.14 | I64: 67981.92 | J64: 0.2352
C65: ISR a Retener del mes | D65: =+D63+D64 -> 64863.091 | G65: 668840.15 | H65: 1276926 | I65: 125485.07 | J65: 0.3
C66: SUBSIDIO | D66: 0 | G66: 1276926 | H66: 1702568 | I66: 307910.81 | J66: 0.32
B67: Deduccion: | C67: ISR | D67: =+D65-D66 -> 64863.091 | G67: 1702568 | H67: 5107703.9 | I67: 444116.23 | J67: 0.34
G68: 5107703.9 | H68: En adelante | I68: 1601862.5 | J68: 0.35
C69: Neto semanal | D69: =+D59-D67 -> 344889.63
C70: Neto esperado | D70: 13228.66
B72: ISR anual | C72: Total de catorcenas | D72: ISR catorcenal
B73: =+D67 -> 64863.091 | C73: =+C56 -> 26.0714 | D73: =+B73/C73 -> 2487.9021
B76: Percepcion | C76: ISR | D76: Neto | E76: Esperado | F76: Diferencia
B77: =+B56 -> 15716.56 | C77: =+D73 -> 2487.9021 | D77: =+B77-C77 -> 13228.658 | E77: 13228.66 | F77: =+D77-E77 -> -0.002114241
F82: RESUMEN
G84: Semanal | H84: Mensual | I84: Mensula Prorrateada | J84: Anual
F85: Base | G85: =+D3 -> 16837.56 | H85: =+E21 -> 24845.895 | I85: =+D40 -> 15715.95 | J85: =+B77 -> 15716.56
F86: Impuesto | G86: =+D11 -> 3608.901 | H86: =+E29 -> 4517.6646 | I86: =+D48 -> 2487.2931 | J86: =+C77 -> 2487.9021
F87: Neto | G87: =+G85-G86 -> 13228.659 | H87: =+H85-H86 -> 20328.231 | I87: =+I85-I86 -> 13228.657 | J87: =+J85-J86 -> 13228.658

Sheet Sheet5
B3: SIMULACION SALARIO
B5: Percepcion:
C6: Sueldo Ordinario | D6: 13518.66
C7: Septimo Dia | D7: 2253.11
C8: Bono Puntualidad | D8: 1577.177
C9: Bono Asistencia | D9: 1577.177
C10: Total Percepcion | D10: 18926.124
B12: Deduccion:
C13: IMSS Trabajador | D13: 450.53602
C14: ISPT Trabajador | D14: 4403.79
C15: Ajuste Moneda | D15: 0
C16: Total Deducciones | D16: 4854.326
C19: Neto a Pagar | D19: 14071.798
C20: Sodexo | D20: 200
C21: Neto + Sodexo | D21: 14271.798
B22: Impuesto Patronal
C23: IMSS Empresa | D23: 1464.6908
C24: Infonavit | D24: 827.4778
C25: RCV | D25: 1032.8578
C26: Impuesto Estatal | D26: 866.81648
C27: Total Patronales | D27: 4191.8429
C29: Costo nomina | D29: 23317.967

Sheet Sheet1
C3: SIMULACION SALARIO
C5: Percepcion: | G5: 30 | I5: 45 | K5: 60 | M5: 90
D6: Sueldo Ordinario | E6: 18719.4 | G6: 18719.4 | I6: 18719.4 | K6: 18719.4 | M6: 18719.4
D7: Septimo Dia | E7: 3119.9 | G7: 3119.9 | I7: 3119.9 | K7: 3119.9 | M7: 3119.9
D8: T. Extra | E8: 0 | G8: 0 | I8: 0 | K8: 0 | M8: 0
D9: Bono Puntualidad | E9: 2183.93 | G9: 2183.93 | I9: 2183.93 | K9: 2183.93 | M9: 2183.93
D10: Bono Asistencia | E10: 2183.93 | G10: 2183.93 | I10: 2183.93 | K10: 2183.93 | M10: 2183.93
D11: Aguinaldo | E11: 23960.832 | G11: 23960.832 | I11: 23960.832 | K11: 23960.832 | M11: 23960.832
D12: Vacaciones | E12: 107511.75 | G12: 107511.75 | I12: 107511.75 | K12: 107511.75 | M12: 107511.75
D13: Prima | E13: 37629.114 | G13: 37629.114 | I13: 37629.114 | K13: 37629.114 | M13: 37629.114
D14: Compensacion | E14: 0 | G14: 93597 | I14: 140395.5 | K14: 187194 | M14: 280791
D15: Total Percepcion | E15: =SUM(E6:E14) -> 195308.86 | G15: =SUM(G6:G14) -> 288905.86 | I15: =SUM(I6:I14) -> 335704.36 | K15: =SUM(K6:K14) -> 382502.86 | M15: =SUM(M6:M14) -> 476099.86
C17: Deduccion:
D18: IMSS Trabajador | E18: 642.78849 | G18: 3240.1052 | I18: 4538.7636 | K18: 5837.422 | M18: 8434.7387
D19: ISPT Trabajador | E19: 113552.73 | G19: 146311.68 | I19: 162691.15 | K19: 179070.63 | M19: 211829.58
D20: Ajuste Moneda
D21: Total Deducciones | E21: =SUM(E18:E20) -> 114195.52 | G21: =SUM(G18:G20) -> 149551.79 | I21: =SUM(I18:I20) -> 167229.91 | K21: =SUM(K18:K20) -> 184908.05 | M21: =SUM(M18:M20) -> 220264.32
D24: Neto a Pagar | E24: =+E15-E21 -> 81113.341 | G24: =+G15-G21 -> 139354.07 | I24: =+I15-I21 -> 168474.45 | K24: =+K15-K21 -> 197594.81 | M24: =+M15-M21 -> 255835.54
D25: Sodexo | E25: 200 | G25: 200 | I25: 200 | K25: 200 | M25: 200
D26: Neto + Sodexo | E26: =+E24+E25 -> 81313.341 | G26: =+G24+G25 -> 139554.07 | I26: =+I24+I25 -> 168674.45 | K26: =+K24+K25 -> 197794.81 | M26: =+M24+M25 -> 256035.54
C27: Impuesto Patronal
D28: IMSS Empresa | E28: 1545.9187 | G28: 7255.3357 | I28: 10110.044 | K28: 12964.753 | M28: 18674.17
D29: Infonavit | E29: 841.925 | G29: 841.925 | I29: 841.925 | K29: 841.925 | M29: 841.925
D30: RCV | E30: 1207.9227 | G30: 6028.1682 | I30: 8438.291 | K30: 10848.414 | M30: 15668.659
D31: Impuesto Estatal | E31: 5859.2658 | G31: 8667.1758 | I31: 10071.131 | K31: 11475.086 | M31: 14282.996
D32: Total Patronales | E32: =SUM(E28:E31) -> 9455.0322 | G32: =SUM(G28:G31) -> 22792.605 | I32: =SUM(I28:I31) -> 29461.391 | K32: =SUM(K28:K31) -> 36130.177 | M32: =SUM(M28:M31) -> 49467.75
E34: =+E15+E25+E32 -> 204963.89 | G34: =+G15+G25+G32 -> 311898.46 | I34: =+I15+I25+I32 -> 365365.75 | K34: =+K15+K25+K32 -> 418833.04 | M34: =+M15+M25+M32 -> 525767.61
M38: =+E15+E25+EFQ32 -> 195508.86

Sheet Sheet2
G3: SIN SODEX
A4: Percepcion:
B5: Sueldo Ordinario | C5: 5136.42 | E5: 4179.54 | G5: 5331 | I5: 4368
B6: Septimo Dia | C6: 856.07 | E6: 696.59 | G6: 888.5 | I6: 728
B7: T. Extra | C7: 0 | E7: 0 | G7: 0 | I7: $ -
B8: Bono Puntualidad | C8: 599.249 | E8: 487.613 | G8: 621.95 | I8: 509.6
B9: Bono Asistencia | C9: 599.249 | E9: 487.613 | G9: 621.95 | I9: 509.6
B10: Total Percepcion | C10: 7190.988 | E10: 5851.356 | G10: 7463.4 | I10: 6115.2
A12: Deduccion:
B13: IMSS Trabajador | C13: 165.72641 | E13: 133.347 | G13: 172.31071 | I13: 139.72
B14: ISPT Trabajador | C14: 1225.24 | E14: 918 | G14: 1289.31 | I14: 974.36
B15: Ajuste Moneda
B16: Total Deducciones | C16: 1390.9664 | E16: 1051.347 | G16: 1461.6207 | I16: 1114.08
B19: Neto a Pagar | C19: 5800.0216 | E19: 4800.009 | G19: 6001.7793 | I19: 5001.12
B20: Sodexo | C20: 200 | E20: 200 | G20: 0 | I20: -
B21: Neto + Sodexo | C21: 6000.0216 | E21: 5000.009 | G21: 6001.7793 | I21: 5001.12
A22: Impuesto Patronal
B23: IMSS Empresa | C23: 497.24173 | E23: 426.06537 | G23: 511.71532 | I23: 440.08
B24: Infonavit | C24: 313.16917 | E24: 254.82789 | G24: 325.03277 | I24: 266.32
B25: RCV | C25: 322.56424 | E25: 262.47273 | G25: 334.78376 | I25: 274.31
B26: Impuesto Estatal | C26: 215.72964 | E26: 175.54068 | G26: 223.902 | I26: 183.46
B27: Total Patronales | C27: 1348.7048 | E27: 1118.9067 | G27: 1395.4339 | I27: 1164.17
C29: 8539.6928 | E29: 6970.2627 | G29: 8858.8339 | I29: 7279.37
C31: =+C21*4 -> 24000.086 | E31: =+E21*4 -> 20000.036 | G31: =+G21*4 -> 24007.117 | I31: =+I21*4 -> 20004.48

Sheet Sheet3
A1: Nota
A2: 0.0658875 | B2: Hyundai
A3: 2.5 | B3: Todas las demas

Sheet 33 Hilos 
B3: SIMULACION SALARIO | G3: SIMULACION SALARIO
B5: Percepcion: | G5: Percepcion:
C6: Sueldo Ordinario | D6: 13518.66 | H6: Sueldo Ordinario | I6: 13518.66
C7: Septimo Dia | D7: 2253.11 | H7: Septimo Dia | I7: 2253.11
C8: Bono Puntualidad | D8: 1577.177 | H8: Bono Puntualidad | I8: 1577.177
C9: Bono Asistencia | D9: 1577.177 | H9: Bono Asistencia | I9: 1577.177
C10: Total Percepcion | D10: 18926.124 | H10: Total Percepcion | I10: 18926.124
B12: Deduccion: | G12: Deduccion:
C13: IMSS Trabajador | D13: 450.53602 | H13: IMSS Trabajador | I13: 450.53602
C14: ISPT Trabajador | D14: 4403.79 | H14: ISPT Trabajador | I14: 4403.79
C15: Ajuste Moneda | D15: 0 | H15: Ajuste Moneda | I15: 0
C16: Total Deducciones | D16: 4854.326 | H16: Total Deducciones | I16: 4854.326
C19: Neto a Pagar | D19: 14071.798 | H19: Neto a Pagar | I19: 14071.798
C20: Sodexo | D20: 200 | H20: Sodexo | I20: 200
C21: Neto + Sodexo | D21: 14271.798 | H21: Neto + Sodexo | I21: 14271.798
B22: Impuesto Patronal | G22: Impuesto Patronal
C23: IMSS Empresa | D23: 1464.6908 | H23: IMSS Empresa | I23: 1464.6908
C24: Infonavit | D24: 827.4778 | H24: Infonavit | I24: 827.4778
C25: RCV | D25: 1032.8578 | H25: RCV | I25: 1032.8578
C26: Impuesto Estatal | D26: 866.81648 | H26: Impuesto Estatal | I26: 866.81648
C27: Total Patronales | D27: 4191.8429 | H27: Total Patronales | I27: 4191.8429
C29: Costo nomina | D29: 23317.967 | H29: Costo nomina | I29: 23317.967
